[
  {
    "newsArray": [
      { "siteName": "IT 之家" },
      { "siteName": "网易科技" },
      { "siteName": "快科技" }
    ],
    "summary": "蔚来汽车推出天穹车尾帐，适配 ES / EC 车型全部车款，经典款售价 3999 元，黑胶款售价 4899 元，7 月 17 日发货，预订赠送户外露营灯 ...",
    "id": "8qFAQ9idjqY",
    "order": 547127,
    "createdAt": "2023-06-17T06:09:14.102Z",
    "title": "蔚来汽车推出天穹车尾帐：适配 ES / EC 车型，预售 3999 元起",
    "score": 0.487101346127936,
    "hasInstantView": false,
    "type": "topic",
    "voteDesc": "",
    "date": "2023-06-17 14:09:14",
    "uuid": "3afd4c0a-0e91-4936-ad05-f5caf6b7b98c"
  },
  {
    "newsArray": [
      { "siteName": "新浪科技" },
      { "siteName": "新浪" },
      { "siteName": "品玩" }
    ],
    "summary": "此前，萝卜快跑全无人自动驾驶运营服务已在北京、武汉、重庆三城落地 ...",
    "id": "8qGGWJrappq",
    "order": 547126,
    "createdAt": "2023-06-17T06:09:10.622Z",
    "title": "萝卜快跑获批在深圳开展全无人商业化试点运营",
    "score": 0.781991740314878,
    "hasInstantView": false,
    "type": "topic",
    "voteDesc": "",
    "date": "2023-06-17 14:09:10",
    "uuid": "116584eb-84f7-4bd3-a581-9a5976816371"
  },
  {
    "newsArray": [{ "siteName": "IT 之家" }, { "siteName": "凤凰科技" }],
    "summary": "IDC 最新发布的《全球笔记本电脑组装产业出货研究报告》显示，2023 年第一季度全球笔记本电脑组装产业因经济下行而遭遇市场需求不振，出货量仅为 3400 万台，环比下滑 14.6%，同比下滑 36.4% ...",
    "id": "8qFjFTxypFQ",
    "order": 547124,
    "createdAt": "2023-06-17T05:49:27.123Z",
    "title": "换机潮叠加AI潮 2024年全球笔记本电脑出货量将实现两位数增长",
    "score": 0.723406140728484,
    "hasInstantView": false,
    "type": "topic",
    "voteDesc": "",
    "date": "2023-06-17 13:49:27",
    "uuid": "e665431d-764f-4345-baed-c91c1e69e050"
  },
  {
    "newsArray": [
      { "siteName": "36Kr" },
      { "siteName": "钛媒体" },
      { "siteName": "中国证券网" }
    ],
    "summary": "联合调查组经勘查现场，调取监控视频发现，6月1日，学生在食堂吃出疑似为“鼠头”的异物，被涉事食堂工作人员事发当日丢弃 ...",
    "id": "8qGL0Bs2cCw",
    "order": 547119,
    "createdAt": "2023-06-17T05:30:50.491Z",
    "title": "江西工职院“6·1”食品安全事件调查处理情况公布：判定异物为老鼠类啮齿动物的头部",
    "score": 0.70965987035156,
    "hasInstantView": false,
    "type": "topic",
    "voteDesc": "",
    "date": "2023-06-17 13:30:50",
    "uuid": "a751c349-b0ea-4b35-960f-9e248a149b84"
  },
  {
    "newsArray": [
      { "siteName": "36Kr" },
      { "siteName": "搜狐" },
      { "siteName": "搜狐" }
    ],
    "summary": "专家组对系统涉及的关键技术和研发路径进行评审，经充分讨论和研判，一致认为拌合站集控式AI生产系统通过验收，满足产业化推广条件 ...",
    "id": "8qGx5mw2hYb",
    "order": 547114,
    "createdAt": "2023-06-17T05:03:34.677Z",
    "title": "四川路桥自研首个可实现产业化智能建造产品",
    "score": 0.760708514591071,
    "hasInstantView": false,
    "type": "topic",
    "voteDesc": "",
    "date": "2023-06-17 13:03:34",
    "uuid": "0a05460e-4578-45f7-ae9a-d3c474cbc06d"
  },
  {
    "newsArray": [
      { "siteName": "搜狐" },
      { "siteName": "和讯汽车" },
      { "siteName": "36Kr" },
      { "siteName": "界面" }
    ],
    "summary": "长安汽车在机构调研时表示，2025年前，打造新一代快充技术，开发新一代高集成、高性能、高安全电池，实现CTV集成效率≥79% ...",
    "id": "8qGJhYUZUlK",
    "order": 547113,
    "createdAt": "2023-06-17T05:02:07.511Z",
    "title": "长安汽车：2025年前突破并应用少稀土磁阻电机等新材料、新结构、新工艺",
    "score": 0.581178938854189,
    "hasInstantView": false,
    "type": "topic",
    "voteDesc": "",
    "date": "2023-06-17 13:02:07",
    "uuid": "99f935c3-0e1c-48e5-b3b5-892008f7a9d0"
  },
  {
    "newsArray": [
      { "siteName": "钛媒体" },
      { "siteName": "搜狐" },
      { "siteName": "36Kr" }
    ],
    "summary": "中信建投研报认为，未来AI算力将综合考虑硬件能力、成本等因素，以混合AI的架构，在边端和云端灵活分配 ...",
    "id": "8qGDCa1bUWc",
    "order": 547107,
    "createdAt": "2023-06-17T04:30:58.237Z",
    "title": "中信建投：建议重点关注物联网模组、智能控制器板块",
    "score": 0.514829282285466,
    "hasInstantView": false,
    "type": "topic",
    "voteDesc": "",
    "date": "2023-06-17 12:30:58",
    "uuid": "92c9654d-42ba-40cf-85d0-7a26fd5d817e"
  },
  {
    "newsArray": [
      { "siteName": "中证网" },
      { "siteName": "澎湃新闻" },
      { "siteName": "新浪" }
    ],
    "summary": "因已连续担任公司独立董事届满六年，张克华向董事会提出辞去独立董事以及在董事会中的其他职务 ...",
    "id": "8qFO7KgbxYM",
    "order": 547104,
    "createdAt": "2023-06-17T04:15:51.653Z",
    "title": "宝钢股份：拟增选复旦法学院副院长陈力教授为独立董事",
    "score": 0.848880872684205,
    "hasInstantView": false,
    "type": "topic",
    "voteDesc": "",
    "date": "2023-06-17 12:15:51",
    "uuid": "09ec064a-0cfb-44ea-b1e4-e65a34904c79"
  },
  {
    "newsArray": [
      { "siteName": "新浪科技" },
      { "siteName": "搜狐" },
      { "siteName": "搜狐" }
    ],
    "summary": "房东说，事发前他正在二楼这间屋子里用吹风机烘干潮湿衣物，因衣物还未完全干透，便将吹风机放在床上继续吹，自己下楼洗衣服 ...",
    "id": "8qEMPbKi3SI",
    "order": 547080,
    "createdAt": "2023-06-17T02:44:01.777Z",
    "title": "吹风机“吹出”一场火灾，使用需谨慎",
    "score": 0.446728800648171,
    "hasInstantView": false,
    "type": "topic",
    "voteDesc": "",
    "date": "2023-06-17 10:44:01",
    "uuid": "f20ff8c0-64e4-481c-9e79-91871d4f2f2c"
  },
  {
    "newsArray": [
      { "siteName": "网易科技" },
      { "siteName": "界面" },
      { "siteName": "界面" }
    ],
    "summary": "而上汽集团旗下自主品牌和合资品牌入选车型高达19款，或成本次新能源下乡活动最大赢家 ...",
    "id": "8qF7d4pXUdi",
    "order": 547076,
    "createdAt": "2023-06-17T02:31:08.861Z",
    "title": "69款车型入选2023年新能源汽车下乡活动，上汽旗下品牌占了19款",
    "score": 0.402282215572291,
    "hasInstantView": false,
    "type": "topic",
    "voteDesc": "",
    "date": "2023-06-17 10:31:08",
    "uuid": "407de1c5-364d-42b3-bffd-8f7e0f7657f7"
  },
  {
    "newsArray": [
      { "siteName": "36Kr" },
      { "siteName": "中证网" },
      { "siteName": "中证网" }
    ],
    "summary": "北交所上市公司汉鑫科技披露《关于公司及相关责任人收到纪律处分决定书的公告》 ...",
    "id": "8qFy4uspzKT",
    "order": 547050,
    "createdAt": "2023-06-17T00:45:54.320Z",
    "title": "对违规行为“零容忍” 北交所对汉鑫科技予以纪律处分",
    "score": 0.823552227943331,
    "hasInstantView": false,
    "type": "topic",
    "voteDesc": "",
    "date": "2023-06-17 08:45:54",
    "uuid": "2fabe423-c27b-4f3a-8fec-e1946e016f6a"
  },
  {
    "newsArray": [
      { "siteName": "IT 之家" },
      { "siteName": "搜狐科技" },
      { "siteName": "凤凰科技" }
    ],
    "summary": "根据美国商标和专利局（USPTO）公示的清单，苹果近期获得了编号为US 11676373 B2 的新专利，暗示 Face ID 将会引入 Mac 平台 ...",
    "id": "8qGpNZ5XiCR",
    "order": 547047,
    "createdAt": "2023-06-17T00:30:45.856Z",
    "title": "苹果新专利获批 暗示Face ID将进入Mac设备",
    "score": 0.776605303659167,
    "hasInstantView": false,
    "type": "topic",
    "voteDesc": "",
    "date": "2023-06-17 08:30:45",
    "uuid": "fe466705-9b34-4c0f-a714-89ccb0a70604"
  },
  {
    "newsArray": [{ "siteName": "IT 之家" }, { "siteName": "凤凰科技" }],
    "summary": "苹果技术副总裁凯文・林奇（Kevin Lynch）近日接受国外科技媒体 CNET 采访，在讨论到 watchOS 10 系统时，他表示苹果希望 Apple Watch 成为你的“世界钥匙”（Key to the World） ...",
    "id": "8qFBAj81TNZ",
    "order": 547046,
    "createdAt": "2023-06-17T00:09:02.537Z",
    "title": "计划成为“万能钥匙”之后 苹果高管暗示Apple Watch下个目标是取代钱包",
    "score": 0.590212504256076,
    "hasInstantView": false,
    "type": "topic",
    "voteDesc": "",
    "date": "2023-06-17 08:09:02",
    "uuid": "6848a569-e54b-43c3-8df4-a8508eb3aeb9"
  },
  {
    "newsArray": [
      { "siteName": "新浪" },
      { "siteName": "澎湃新闻" },
      { "siteName": "新浪" }
    ],
    "summary": "这些天，多部门召开新闻发布会或发布相关政策，在老百姓关心的钱袋子、房子、车子等方面，释放新的信息 ...",
    "id": "8qGnpFFVomc",
    "order": 547044,
    "createdAt": "2023-06-16T23:45:38.802Z",
    "title": "多部门召开发布会或发布政策，房子、车子、钱袋子都有新动向",
    "score": 0.536900018185964,
    "hasInstantView": false,
    "type": "topic",
    "voteDesc": "",
    "date": "2023-06-17 07:45:38",
    "uuid": "a7b17afb-4124-4a0c-8aed-82cf13edc4de"
  },
  {
    "newsArray": [
      { "siteName": "新浪" },
      { "siteName": "网易科技" },
      { "siteName": "新浪" }
    ],
    "summary": "特斯拉“股价起飞”开始于5月24日，巧合的是，5月25日福特与特斯拉宣布达成协议，福特电动汽车买家将从2024年初开始得以使用特斯拉的超级充电站网络，享受路上快速充电服务 ...",
    "id": "8qG0YEPoVpS",
    "order": 547034,
    "createdAt": "2023-06-16T21:01:44.415Z",
    "title": "特斯拉超长连涨后华尔街信心不减：类比“亚马逊云”和“苹果服务”的高光时刻来了",
    "score": 0.458839365031107,
    "hasInstantView": false,
    "type": "topic",
    "voteDesc": "",
    "date": "2023-06-17 05:01:44",
    "uuid": "242a8b75-85fa-4dd0-84a6-298df8def4b7"
  },
  {
    "newsArray": [
      { "siteName": "新浪" },
      { "siteName": "新浪" },
      { "siteName": "新浪科技" }
    ],
    "summary": "燃石医学涨超14%，亿咖通科技涨超11%，复朗集团涨超9%，比特数字涨超8%，兰亭集势涨超7%，虎牙涨超5%，趣店、阿特斯涨超4%，水滴公司、搜狐、大健云仓涨超3%，新氧、格林酒店、晶科能源涨超2%，叮咚买菜、量子之歌、BOSS直聘涨超1% ...",
    "id": "8qEwIVrM2cV",
    "order": 547033,
    "createdAt": "2023-06-16T21:01:37.297Z",
    "title": "热门中概股周五多数下跌 金山云陆金所跌超7% 亚朵集团B站跌超4%",
    "score": 0.525541156537237,
    "hasInstantView": false,
    "type": "topic",
    "voteDesc": "",
    "date": "2023-06-17 05:01:37",
    "uuid": "6f1cf065-e90e-47fd-8b88-35df9806768a"
  },
  {
    "newsArray": [
      { "siteName": "新浪" },
      { "siteName": "新浪" },
      { "siteName": "新浪" },
      { "siteName": "36Kr" }
    ],
    "summary": "Adobe公布的第二财季业绩显示，公司在截至6月2日的三个月内实现48.2亿美元的营收，不仅创下历史新高，还强于分析师先前预期的47.7亿美元 ...",
    "id": "8qFK2DsxtbM",
    "order": 547030,
    "createdAt": "2023-06-16T19:15:40.323Z",
    "title": "人工智能加持，Adobe营收创新高",
    "score": 0.41645287622227,
    "hasInstantView": false,
    "type": "topic",
    "voteDesc": "",
    "date": "2023-06-17 03:15:40",
    "uuid": "b4878879-fe1b-45bc-bbd7-d152f72ec900"
  }
]
