[
  {
    "newsArray": [{ "siteName": "IT 之家" }, { "siteName": "凤凰科技" }],
    "summary": "其中一个有趣的变化是，用户现在可以直接在 Apple Watch 上添加银行卡到 Apple Pay，而不需要使用 iPhone ...",
    "id": "8qBanUL8h6p",
    "order": 545577,
    "createdAt": "2023-06-13T20:57:12.542Z",
    "title": "无需iPhone 苹果watchOS 10支持直接在Apple Watch上添加Apple Pay银行卡",
    "score": 0.549252167422073,
    "hasInstantView": false,
    "type": "topic",
    "voteDesc": "",
    "date": "2023-06-14 04:57:12",
    "uuid": "dcde0d22-9471-455f-93fb-00bf82780615"
  }
]
