[
  {
    "newsArray": [
      { "siteName": "新浪" },
      { "siteName": "澎湃新闻" },
      { "siteName": "新浪" }
    ],
    "summary": "6月30日晚间，融创中国（01918.HK）公布股东特别大会投票表决结果，第1项至第3项普通决议案均获得超过50%的赞成票数，因此该项决议案获正式通过为公司普通决议案 ...",
    "id": "8r2UiGdXpcJ",
    "order": 552196,
    "createdAt": "2023-07-01T08:02:08.434Z",
    "title": "融创中国：债务重组相关决议案获股东特别大会投票通过",
    "score": 0.898176908619486,
    "hasInstantView": false,
    "type": "topic",
    "voteDesc": "",
    "date": "2023-07-01 16:02:08",
    "uuid": "2bc90514-1f11-4f17-8996-b28b4c6c7298"
  },
  {
    "newsArray": [
      { "siteName": "新浪科技" },
      { "siteName": "新浪" },
      { "siteName": "虎嗅" }
    ],
    "summary": "一份法庭文件显示，在截至2022年6月的12个月里，微软Azure云服务去年营收规模约为340亿美元，不及竞争对手亚马逊云AWS同期720亿美元营收规模的一半 ...",
    "id": "8r2Vbke7zrY",
    "order": 552191,
    "createdAt": "2023-07-01T07:31:03.440Z",
    "title": "微软云Azure营收规模曝光，不及亚马逊AWS的一半",
    "score": 0.517964521558827,
    "hasInstantView": false,
    "type": "topic",
    "voteDesc": "",
    "date": "2023-07-01 15:31:03",
    "uuid": "183d1cdd-d328-4d3c-81db-987a42a8aa0d"
  },
  {
    "newsArray": [
      { "siteName": "IT 之家" },
      { "siteName": "凤凰科技" },
      { "siteName": "搜狐科技" }
    ],
    "summary": "苹果于 5 月 19 日发布 iOS / iPadOS 16.5 更新（内部版本号：20F66），相比较此前版本，更新幅度并不大，主要修复重要的 BUG，在新功能方面并未引入太多 ...",
    "id": "8r3D6H4bE00",
    "order": 552187,
    "createdAt": "2023-07-01T07:15:56.522Z",
    "title": "苹果关闭iOS 16.5验证通道 已升级iPhone用户无法降级",
    "score": 0.711785873388209,
    "hasInstantView": false,
    "type": "topic",
    "voteDesc": "",
    "date": "2023-07-01 15:15:56",
    "uuid": "57a77781-828d-434f-b329-ea3678c06a9d"
  },
  {
    "newsArray": [
      { "siteName": "新浪" },
      { "siteName": "澎湃新闻" },
      { "siteName": "钛媒体" }
    ],
    "summary": "6月30日晚间，金科股份宣布公司与中国长城资产管理股份有限公司（以下简称“长城资管”）的全资子公司长城国富置业有限公司（以下简称“长城国富”）签订《战略投资框架协议》 ...",
    "id": "8r372IBSZuQ",
    "order": 552184,
    "createdAt": "2023-07-01T07:03:28.524Z",
    "title": "金科股份：与长城资管子公司签订战略投资框架协议，其有意参与预重整投资",
    "score": 0.814611281098665,
    "hasInstantView": false,
    "type": "topic",
    "voteDesc": "",
    "date": "2023-07-01 15:03:28",
    "uuid": "c176d292-d828-4070-bf8e-c5892e6c92ce"
  },
  {
    "newsArray": [
      { "siteName": "中国证券网" },
      { "siteName": "澎湃新闻" },
      { "siteName": "钛媒体" }
    ],
    "summary": "在国家知识产权局举行的6月例行新闻发布会上，国家知识产权局新闻发言人、知识产权保护司司长张志成发布了《2022年中国知识产权保护状况》白皮书 ...",
    "id": "8r2NLqZdOff",
    "order": 552173,
    "createdAt": "2023-07-01T06:02:45.303Z",
    "title": "国知局：截至去年底中国发明专利有效量同比增长17.1%",
    "score": 0.683911740134582,
    "hasInstantView": false,
    "type": "topic",
    "voteDesc": "",
    "date": "2023-07-01 14:02:45",
    "uuid": "4ed5885d-1774-435c-a6c9-7b1f4f32e532"
  },
  {
    "newsArray": [
      { "siteName": "澎湃新闻" },
      { "siteName": "中国证券网" },
      { "siteName": "中国证券网" }
    ],
    "summary": "当日起，长三角铁路将实行新列车运行图，增开长三角前往北京、河南、江西、山东、甘肃等9对直通方向旅客列车，并在长三角区域内主要城市间加开多趟管内旅客列车，尽力满足暑期旅客出行需求 ...",
    "id": "8r2IqXgQfHc",
    "order": 552164,
    "createdAt": "2023-07-01T05:15:38.674Z",
    "title": "长三角铁路暑运明日启动，预计发送旅客超1.5亿人次创新高",
    "score": 0.542735864363186,
    "hasInstantView": false,
    "type": "topic",
    "voteDesc": "",
    "date": "2023-07-01 13:15:38",
    "uuid": "8e7a2d8c-0781-4148-9ee7-9afb58b5812e"
  },
  {
    "newsArray": [
      { "siteName": "网易科技" },
      { "siteName": "界面" },
      { "siteName": "IT 之家" }
    ],
    "summary": "青藏铁路西宁至格尔木段“复兴号”动车组今天正式投入运营，标志着青藏铁路正式进入动车时代 ...",
    "id": "8r3R3U2huIc",
    "order": 552160,
    "createdAt": "2023-07-01T04:40:24.560Z",
    "title": "“复兴号”正式在青藏铁路投入运行 青藏铁路正式进入动车时代",
    "score": 0.438440259733461,
    "hasInstantView": false,
    "type": "topic",
    "voteDesc": "",
    "date": "2023-07-01 12:40:24",
    "uuid": "4a6482a6-7828-4aa3-89d4-1260c06695b7"
  },
  {
    "newsArray": [
      { "siteName": "新浪" },
      { "siteName": "界面" },
      { "siteName": "中国证券网" },
      { "siteName": "澎湃新闻" }
    ],
    "summary": "阿根廷经济部6月30日宣布，阿根廷政府当天使用特别提款权和人民币向国际货币基金组织（IMF）偿付27亿美元到期外债 ...",
    "id": "8r3zVwsXaWK",
    "order": 552158,
    "createdAt": "2023-07-01T04:30:52.539Z",
    "title": "阿根廷首次使用人民币偿付到期外债",
    "score": 0.805712016306581,
    "hasInstantView": false,
    "type": "topic",
    "voteDesc": "",
    "date": "2023-07-01 12:30:52",
    "uuid": "38692dcf-d4db-42d7-96c8-b98222cc1940"
  },
  {
    "newsArray": [
      { "siteName": "IT 之家" },
      { "siteName": "TechWeb" },
      { "siteName": "凤凰科技" }
    ],
    "summary": "LG Innotek 计划投资 1.3 万亿韩元（IT之家备注：当前约 71.5 亿元人民币），在越南海防市（Haiphong）扩建一条摄像头模块生产线 ...",
    "id": "8r3KfOAGJTr",
    "order": 552149,
    "createdAt": "2023-07-01T04:15:54.896Z",
    "title": "产能翻番，苹果代工厂LG Innotek斥资71.5亿元扩建越南摄像头模组工厂",
    "score": 0.698415802806773,
    "hasInstantView": false,
    "type": "topic",
    "voteDesc": "",
    "date": "2023-07-01 12:15:54",
    "uuid": "d65af973-aa27-45f6-8914-198823924a85"
  },
  {
    "newsArray": [
      { "siteName": "快科技" },
      { "siteName": "钛媒体" },
      { "siteName": "凤凰科技" }
    ],
    "summary": "根据新出口管制条例规定，ASML需要向荷兰政府申请出口许可证才能发运最先进的浸润式DUV系统（即TWINSCAN NXT：2000i及后续推出的浸润式光刻系统） ...",
    "id": "8r3NPbOlwVR",
    "order": 552147,
    "createdAt": "2023-07-01T04:01:49.734Z",
    "title": "荷兰推半导体出口管制新规，ASML确认部分DUV光刻机将实施出口许可",
    "score": 0.55975299411352,
    "hasInstantView": false,
    "type": "topic",
    "voteDesc": "",
    "date": "2023-07-01 12:01:49",
    "uuid": "0e95b994-05f1-42f5-8616-7e560164e6b1"
  },
  {
    "newsArray": [
      { "siteName": "澎湃新闻" },
      { "siteName": "新浪" },
      { "siteName": "钛媒体" }
    ],
    "summary": "河南、江西、河北等地落地执行第八批国家组织药品集中带量采购中选结果，本次集采中选药品涵盖抗感染、心脑血管疾病、抗过敏、精神疾病等治疗用药，平均降幅达56% ...",
    "id": "8r3FsViaYJY",
    "order": 552131,
    "createdAt": "2023-07-01T02:46:30.362Z",
    "title": "第八批国家组织药品集采今起在全国落地实施，平均降幅56%",
    "score": 0.705251098680644,
    "hasInstantView": false,
    "type": "topic",
    "voteDesc": "",
    "date": "2023-07-01 10:46:30",
    "uuid": "7aba3a9c-d721-47a1-b751-655a5dc74548"
  },
  {
    "newsArray": [
      { "siteName": "澎湃新闻" },
      { "siteName": "新浪" },
      { "siteName": "新浪" }
    ],
    "summary": "紧随其后的分别为华润置地、招商蛇口、碧桂园、龙湖集团、绿城中国、建发房产和滨江集团，销售额分别为1702.2亿元、1663.5亿元、1609亿元、985.1亿元、982.6亿元、953.3亿元和925.8亿元 ...",
    "id": "8r3FruHUoXC",
    "order": 552130,
    "createdAt": "2023-07-01T02:30:48.240Z",
    "title": "报告：6月楼市成交未迎止跌行情，热点城市和热点项目个数减少",
    "score": 0.517389094261598,
    "hasInstantView": false,
    "type": "topic",
    "voteDesc": "",
    "date": "2023-07-01 10:30:48",
    "uuid": "3d9b4940-0200-4156-b34a-0692a45de2b5"
  },
  {
    "newsArray": [{ "siteName": "网易科技" }, { "siteName": "IT 之家" }],
    "summary": "台积电发言人表示，本次网络安全事件导致“与服务器初始设置和配置相关”的数据泄露，但台积电客户信息并未受到影响 ...",
    "id": "8r33mdGoCao",
    "order": 552104,
    "createdAt": "2023-07-01T00:02:27.946Z",
    "title": "台积电遭攻击，黑客用数据威胁索要 7000 万美元赎金",
    "score": 0.696440112819647,
    "hasInstantView": false,
    "type": "topic",
    "voteDesc": "",
    "date": "2023-07-01 08:02:27",
    "uuid": "89c80598-f4af-42eb-8a58-08ddcaa68b75"
  },
  {
    "newsArray": [
      { "siteName": "新浪" },
      { "siteName": "新浪科技" },
      { "siteName": "IT 之家" }
    ],
    "summary": "截至周五收盘，苹果公司的股价上涨2.3%，至193.97美元，市值达到3.05万亿美元 ...",
    "id": "8r2GgVVXEPB",
    "order": 552098,
    "createdAt": "2023-06-30T23:20:14.759Z",
    "title": "苹果成为首家收盘市值达到3万亿美元的公司",
    "score": 0.439293647778046,
    "hasInstantView": false,
    "type": "topic",
    "voteDesc": "",
    "date": "2023-07-01 07:20:14",
    "uuid": "37fa2818-57ba-4b01-bf91-872c8dcf2ee1"
  },
  {
    "newsArray": [
      { "siteName": "新浪" },
      { "siteName": "新浪科技" },
      { "siteName": "新浪科技" }
    ],
    "summary": "金融数据解决方案Refinitiv预计，特斯拉今年第二季度将交付44.5万辆电动汽车，环比增长5%，创历史新高 ...",
    "id": "8r2Zwvi7q07",
    "order": 552095,
    "createdAt": "2023-06-30T22:30:37.058Z",
    "title": "机构：特斯拉第二季度交付量或创历史新高",
    "score": 0.578323637830288,
    "hasInstantView": false,
    "type": "topic",
    "voteDesc": "",
    "date": "2023-07-01 06:30:37",
    "uuid": "3009dbe8-2e2d-4803-b36a-3de055d98f59"
  },
  {
    "newsArray": [{ "siteName": "IT 之家" }, { "siteName": "新浪科技" }],
    "summary": "西铁城介绍，LUNA Program 可利用机芯内部独特的计算程序，根据接收到无线电波所包含的日期信息计算出当天的月相，月相将显示在表盘 6 点钟位置的月相显示区中 ...",
    "id": "8r2rX5VLrx0",
    "order": 552089,
    "createdAt": "2023-06-30T22:11:03.032Z",
    "title": "西铁城推出世界首款可自动计算月相的手表，售价 12.65 万日元起",
    "score": 0.541011630144345,
    "hasInstantView": false,
    "type": "topic",
    "voteDesc": "",
    "date": "2023-07-01 06:11:03",
    "uuid": "f0f834db-f4d4-498e-8e54-267e0d223043"
  },
  {
    "newsArray": [{ "siteName": "IT 之家" }, { "siteName": "网易科技" }],
    "summary": "《精灵宝可梦GO》游戏开发商 Niantic 近日宣布启动内部架构变革，裁员 230 名员工、中止非核心游戏项目，以及关闭洛杉矶工作室 ...",
    "id": "8r1V52HhEeH",
    "order": 552087,
    "createdAt": "2023-06-30T22:10:17.341Z",
    "title": "Niantic 转向“小而精”发展：裁员 230 人、中止非核心游戏项目",
    "score": 0.806048062263282,
    "hasInstantView": false,
    "type": "topic",
    "voteDesc": "",
    "date": "2023-07-01 06:10:17",
    "uuid": "ea4879ce-c51c-4690-8bc5-15da84723f69"
  },
  {
    "newsArray": [
      { "siteName": "澎湃新闻" },
      { "siteName": "中国证券网" },
      { "siteName": "新浪" }
    ],
    "summary": "表现在试点地区收到境外金融机构等提交的开展金融服务申请后，原则上要在120天内作出决定 ...",
    "id": "8r2KuuPn1Cf",
    "order": 552086,
    "createdAt": "2023-06-30T22:01:22.760Z",
    "title": "央行：支持试点地区企业和个人依法跨境购买境外金融服务",
    "score": 0.669212017010542,
    "hasInstantView": false,
    "type": "topic",
    "voteDesc": "",
    "date": "2023-07-01 06:01:22",
    "uuid": "22b14dfd-91f1-4901-bed6-448ac7302c07"
  }
]
