[
  {
    "newsArray": [
      { "siteName": "华尔街见闻" },
      { "siteName": "36Kr" },
      { "siteName": "财联社" }
    ],
    "summary": "卡塔尔运营的五艘液化天然气船自周五以来被叫停，原因是为了避免胡塞武装袭击和美国领导的袭击所带来的风险。虽然胡塞武装尚未袭击天然气船只，但卡塔尔仍不愿通过红海南端通道。",
    "id": "8WMXG8zDrms",
    "order": 1705290061209,
    "createdAt": "2024-01-15T03:41:02.000Z",
    "publishDate": "2024-01-15T03:41:01.209Z",
    "title": "卡塔尔据悉暂停通过红海运输液化天然气",
    "type": "topic",
    "up": false,
    "date": "2024-01-15 11:41:02",
    "uuid": "bff274ff-95f9-48e5-a765-ab92f087ed86"
  },
  {
    "newsArray": [
      { "siteName": "动脉网" },
      { "siteName": "动脉网" },
      { "siteName": "36Kr" }
    ],
    "summary": "和缓医疗推出企业医疗服务产品“司医”，支持钉钉、企微、飞书三大协同办公平台，提供无限量24小时视频医生服务。",
    "id": "8WMUhvWrE2a",
    "order": 1705289335913,
    "createdAt": "2024-01-15T03:28:55.000Z",
    "publishDate": "2024-01-15T03:28:55.913Z",
    "title": "和缓医疗发布整合医疗服务产品“司医”",
    "type": "topic",
    "up": false,
    "date": "2024-01-15 11:28:55",
    "uuid": "63c75ec7-d185-4893-8065-fb16d60af03f"
  },
  {
    "newsArray": [
      { "siteName": "DoNews" },
      { "siteName": "IT 之家" },
      { "siteName": "财联社" }
    ],
    "summary": "LG电子在美国得克萨斯州启动电动汽车充电桩工厂，占地面积5500平方米，年产1万台以上充电桩 ...",
    "id": "8WMUOpf4TH3",
    "order": 1705289328820,
    "createdAt": "2024-01-15T03:28:48.000Z",
    "publishDate": "2024-01-15T03:28:48.820Z",
    "title": "LG电子启动美国充电桩工厂 年产能1万个",
    "type": "topic",
    "up": false,
    "date": "2024-01-15 11:28:48",
    "uuid": "d9ebd446-7c1c-455a-b480-a877ee045f57"
  },
  {
    "newsArray": [
      { "siteName": "36Kr" },
      { "siteName": "中国证券网" },
      { "siteName": "财联社" },
      { "siteName": "界面" }
    ],
    "summary": "互影科技、阅文集团、上影元和上影制作联合推出双人互动影游《谍影成双》，这是一款创新型双人联机叙事作品，上影元首次涉足互动影游领域。上影制作参与其中，致力于打造“海派精品” ...",
    "id": "8WMUOtYd6xz",
    "order": 1705288859578,
    "createdAt": "2024-01-15T03:19:07.000Z",
    "publishDate": "2024-01-15T03:20:59.578Z",
    "title": "上海电影公布首个互动影游项目《谍影成双》",
    "type": "topic",
    "up": false,
    "date": "2024-01-15 11:19:07",
    "uuid": "d9c717f0-7348-40c9-be5d-0f28925da46e"
  },
  {
    "newsArray": [
      { "siteName": "财联社" },
      { "siteName": "界面" },
      { "siteName": "36Kr" },
      { "siteName": "中国证券网" }
    ],
    "summary": "券商股震荡上涨，国盛金控涨幅超过9%，天风证券、指南针、华鑫股份、西南证券、首创证券等纷纷跟涨。",
    "id": "8WMT1hO3Zte",
    "order": 1705287659552,
    "createdAt": "2024-01-15T03:01:00.000Z",
    "publishDate": "2024-01-15T03:00:59.552Z",
    "title": "券商股震荡拉升，国盛金控涨超9%",
    "type": "topic",
    "up": false,
    "date": "2024-01-15 11:01:00",
    "uuid": "bf61e9cf-aae4-4c78-92d8-776efc0bb90c"
  },
  {
    "newsArray": [
      { "siteName": "财联社" },
      { "siteName": "新浪科技" },
      { "siteName": "界面" },
      { "siteName": "界面" }
    ],
    "summary": "1月15日，港股航运股表现强劲，中远海能、中远海控和东方海外国际股价均有上涨。中远海能涨幅超过6%，中远海控涨幅超过3%，东方海外国际涨幅超过2%。",
    "id": "8WMQ7MVsNw6",
    "order": 1705287043631,
    "createdAt": "2024-01-15T02:40:55.000Z",
    "publishDate": "2024-01-15T02:50:43.631Z",
    "title": "港股航运股走强，中远海能涨超6%",
    "type": "topic",
    "up": false,
    "date": "2024-01-15 10:40:55",
    "uuid": "33ce88e4-5da3-478c-b0c6-0075ccd64273"
  },
  {
    "newsArray": [
      { "siteName": "新浪科技" },
      { "siteName": "智通财经" },
      { "siteName": "36Kr" }
    ],
    "summary": "迪士尼正与美国国家橄榄球联盟（NFL）就后者持有ESPN业务股权进行深入谈判。可能的交易内容包括，ESPN掌控NFL Media，包括NFL Network等，而NFL则获得ESPN的股权 ...",
    "id": "8WMOhH1vQ9W",
    "order": 1705290380528,
    "createdAt": "2024-01-15T02:37:13.000Z",
    "publishDate": "2024-01-15T03:46:20.528Z",
    "title": "传迪士尼正就让NFL入股ESPN进行谈判",
    "type": "topic",
    "up": false,
    "date": "2024-01-15 10:37:13",
    "uuid": "4927cec3-5ab3-4742-84fb-bcc8cd782bd9"
  },
  {
    "newsArray": [
      { "siteName": "36Kr" },
      { "siteName": "界面" },
      { "siteName": "财联社" }
    ],
    "summary": "贝莱德宣布任命范华为中国区负责人，张鹏军为贝莱德建信理财有限责任公司总经理。范华曾担任招银理财首席投资官，加入贝莱德建信理财后担任领导角色 ...",
    "id": "8WMQpdNozEQ",
    "order": 1705286231460,
    "createdAt": "2024-01-15T02:37:12.000Z",
    "publishDate": "2024-01-15T02:37:11.460Z",
    "title": "贝莱德任命范华为中国区负责人",
    "type": "topic",
    "up": false,
    "date": "2024-01-15 10:37:12",
    "uuid": "912c030a-7378-46b8-bf85-ef30d2172b87"
  },
  {
    "newsArray": [
      { "siteName": "腾讯网" },
      { "siteName": "环球网科技" },
      { "siteName": "36Kr" }
    ],
    "summary": "国家邮政局预测，2023年我国快递业务量和业务收入将分别达到1320亿件和1.2万亿元，同比增长19.5%和14.5% ...",
    "id": "8WMJzIBL3nq",
    "order": 1705285881166,
    "createdAt": "2024-01-15T02:31:22.000Z",
    "publishDate": "2024-01-15T02:31:21.166Z",
    "title": "快递物流新趋势：小包裹业务量及收入占比持续攀升",
    "type": "topic",
    "up": false,
    "date": "2024-01-15 10:31:22",
    "uuid": "5e41e365-6123-434c-be0a-3ad94e55224c"
  },
  {
    "newsArray": [
      { "siteName": "i黑马" },
      { "siteName": "IT 之家" },
      { "siteName": "凤凰科技" }
    ],
    "summary": "北京市发改委发布一季度经济发展政策公告，提及宁德时代将在北京建设工厂，理想汽车计划建设零部件生产基地 ...",
    "id": "8WMCtGKKkSw",
    "order": 1705285338779,
    "createdAt": "2024-01-15T02:22:18.000Z",
    "publishDate": "2024-01-15T02:22:18.779Z",
    "title": "消息人士：宁德时代北京工厂已开工建设",
    "type": "topic",
    "up": false,
    "date": "2024-01-15 10:22:18",
    "uuid": "6aa19999-ac16-43b4-af88-5c78e6a62389"
  },
  {
    "newsArray": [
      { "siteName": "澎湃新闻" },
      { "siteName": "36Kr" },
      { "siteName": "财联社" },
      { "siteName": "新浪科技" },
      { "siteName": "新浪科技" },
      { "siteName": "中国证券网" }
    ],
    "summary": "广州市代市长孙志洋在第十六届人民代表大会第四次会议上作政府工作报告，预计2023年地区生产总值突破3万亿元，社会消费品零售总额和商品进出口总值连续三年双双超过1万亿元，固定资产投资超过8600亿元，创历史新高。",
    "id": "8WMNyEhqVeU",
    "order": 1705290464842,
    "createdAt": "2024-01-15T02:22:14.000Z",
    "publishDate": "2024-01-15T03:47:44.842Z",
    "title": "广州2023年GDP预计突破３万亿元",
    "type": "topic",
    "up": false,
    "date": "2024-01-15 10:22:14",
    "uuid": "b50e977a-a4f8-4f61-9790-f4d3619a451f"
  },
  {
    "newsArray": [
      { "siteName": "中关村在线" },
      { "siteName": "网易科技" },
      { "siteName": "IT 之家" }
    ],
    "summary": "天舟七号船箭组合体将于近期进行转运并垂直进入发射区。文昌市公安局已发布交通管制预告，将于2024年1月17日至18日对部分道路进行管制 ...",
    "id": "8WMGojZndMc",
    "order": 1705285238219,
    "createdAt": "2024-01-15T02:20:38.000Z",
    "publishDate": "2024-01-15T02:20:38.219Z",
    "title": "天舟七号船箭组合体今日进行转运，预计本周发射",
    "type": "topic",
    "up": false,
    "date": "2024-01-15 10:20:38",
    "uuid": "6bddce92-9808-439f-ada0-0d81608c5404"
  },
  {
    "newsArray": [
      { "siteName": "投资圈" },
      { "siteName": "动脉网" },
      { "siteName": "动脉网" }
    ],
    "summary": "国内连锁独立血液透析中心头部企业达康医疗宣布完成新一轮融资，由十月资本独家投资。达康医疗将进一步加快行业整合步伐，推进独立血透中心连锁化进程 ...",
    "id": "8WMIHPo6arf",
    "order": 1705284963163,
    "createdAt": "2024-01-15T02:16:04.000Z",
    "publishDate": "2024-01-15T02:16:03.163Z",
    "title": "【首发】达康医疗宣布获得新一轮融资 十月资本独家投资",
    "type": "topic",
    "up": false,
    "date": "2024-01-15 10:16:04",
    "uuid": "a8285fd0-c490-4124-b5e1-78f0a138c3fe"
  },
  {
    "newsArray": [
      { "siteName": "凤凰科技" },
      { "siteName": "搜狐科技" },
      { "siteName": "快科技" },
      { "siteName": "搜狐科技" },
      { "siteName": "腾讯网" },
      { "siteName": "搜狐科技" },
      { "siteName": "搜狐科技" },
      { "siteName": "搜狐科技" },
      { "siteName": "快科技" },
      { "siteName": "搜狐科技" },
      { "siteName": "和讯网" },
      { "siteName": "搜狐科技" }
    ],
    "summary": "1月15日，Apple（中国大陆）官网上线了活动预告，宣布将于1月18日-21日开启“迎新春限时优惠”，其中提到多款苹果产品将迎来降价 ...",
    "id": "8WMQtjmNus0",
    "order": 1705290599556,
    "createdAt": "2024-01-15T02:11:28.000Z",
    "publishDate": "2024-01-15T03:49:59.556Z",
    "title": "苹果中国官网宣布降价，最高可省800元",
    "type": "topic",
    "up": false,
    "date": "2024-01-15 10:11:28",
    "uuid": "98119f5f-15d5-40cc-a3a5-b2e8895c0339"
  },
  {
    "newsArray": [
      { "siteName": "环球网科技" },
      { "siteName": "凤凰科技" },
      { "siteName": "IT 之家" }
    ],
    "summary": "深圳理工大学药学院教授赵佳伟和哈佛大学医学院附属波士顿儿童医院杰出副教授Vijay Sankaran团队在《细胞》杂志上发表最新研究 ...",
    "id": "8WKgCtfSBaP",
    "order": 1705284645923,
    "createdAt": "2024-01-15T02:10:45.000Z",
    "publishDate": "2024-01-15T02:10:45.923Z",
    "title": "中国科学家合作发现白血病全新遗传致病因子，为早期筛查与干预提供新思路",
    "type": "topic",
    "up": false,
    "date": "2024-01-15 10:10:45",
    "uuid": "c69bc2fd-cf20-4402-bc86-94f42b294f4c"
  },
  {
    "newsArray": [
      { "siteName": "腾讯网" },
      { "siteName": "腾讯网" },
      { "siteName": "腾讯网" },
      { "siteName": "新浪科技" }
    ],
    "summary": "旅游板块表现强势，西安旅游涨停，曲江文旅、长白山、天目湖等跟涨。2024年春运从1月26日开始，至3月5日结束，预计营业性客运量比2023年同期有较大增长 ...",
    "id": "8WMQq0hU2h6",
    "order": 1705287066649,
    "createdAt": "2024-01-15T02:05:47.000Z",
    "publishDate": "2024-01-15T02:51:06.649Z",
    "title": "旅游板块表现强势 机构看好2024年国内旅游需求的持续性和高景气",
    "type": "topic",
    "up": false,
    "date": "2024-01-15 10:05:47",
    "uuid": "1a18ddf6-370f-4996-baae-59a63912660b"
  },
  {
    "newsArray": [
      { "siteName": "搜狐科技" },
      { "siteName": "IT 之家" },
      { "siteName": "开源中国" }
    ],
    "summary": "Git开发人员正在讨论在代码库中使用Rust编程语言，以补充现有的C和Python语言。作者认为Rust的引入可以降低内存安全错误、数据争用、内存泄漏等风险，并在重构或引入新代码时更容易 ...",
    "id": "8WKrwAlqmqn",
    "order": 1705284116443,
    "createdAt": "2024-01-15T02:01:56.000Z",
    "publishDate": "2024-01-15T02:01:56.443Z",
    "title": "Git 开发人员讨论引入 Rust 的可能性",
    "type": "topic",
    "up": false,
    "date": "2024-01-15 10:01:56",
    "uuid": "f6f30083-b81a-48ac-9b39-641db2329fb6"
  },
  {
    "newsArray": [
      { "siteName": "界面" },
      { "siteName": "新浪科技" },
      { "siteName": "新浪科技" },
      { "siteName": "证券时报网" },
      { "siteName": "腾讯网" },
      { "siteName": "腾讯网" }
    ],
    "summary": "本文主要概括了以下内容： 1. 股票市场相关，包括国盛金控吸收合并全资子公司国盛证券，东方通等公司拟回购股份，山东黄金董事王立君和银泰黄金董事张于先后辞职等 ...",
    "id": "8WLc7SwYUZ4",
    "order": 1705285242902,
    "createdAt": "2024-01-15T01:51:17.000Z",
    "publishDate": "2024-01-15T02:20:42.902Z",
    "title": "国盛金控拟吸收合并国盛证券",
    "type": "topic",
    "up": false,
    "date": "2024-01-15 09:51:17",
    "uuid": "76cf7165-1e28-49e7-b3bd-589fae407354"
  },
  {
    "newsArray": [
      { "siteName": "界面" },
      { "siteName": "36Kr" },
      { "siteName": "36Kr" },
      { "siteName": "财联社" }
    ],
    "summary": "恒生科技指数大跌1.73%，百度、小鹏汽车、快手等跌幅超5%，京东、B站跌超2%。",
    "id": "8WMPZn339bO",
    "order": 1705283475685,
    "createdAt": "2024-01-15T01:51:15.000Z",
    "publishDate": "2024-01-15T01:51:15.685Z",
    "title": "恒生科技指数跌超1%，百度集团跌超7%",
    "type": "topic",
    "up": false,
    "date": "2024-01-15 09:51:15",
    "uuid": "9f849328-71bc-4914-90dc-b0ec001d0888"
  },
  {
    "newsArray": [
      { "siteName": "36Kr" },
      { "siteName": "动脉网" },
      { "siteName": "动脉网" },
      { "siteName": "猎云网" },
      { "siteName": "投中网" }
    ],
    "summary": "近日，上海英捷信医疗科技有限公司（简称“英捷信”）完成数千万元Pre-A轮融资。这笔资金将用于加速多条全自动生产线的投产、新产品开发和海内外布局，以满足全球自我给药系统的持续增长需求 ...",
    "id": "8WMIH3DrMDO",
    "order": 1705281929238,
    "createdAt": "2024-01-15T01:25:29.000Z",
    "publishDate": "2024-01-15T01:25:29.238Z",
    "title": "【首发】打造国产注射笔行业标杆，英捷信医疗完成数千万元Pre-A轮融资",
    "type": "topic",
    "up": false,
    "date": "2024-01-15 09:25:29",
    "uuid": "5ca3195f-a06d-492f-b140-0fa56415d70e"
  },
  {
    "newsArray": [
      { "siteName": "界面" },
      { "siteName": "36Kr" },
      { "siteName": "界面" }
    ],
    "summary": "中国银河证券研报预测，在北交所交易热度持续的情况下，板块或将震荡行情。2024年投资北交所板块，建议关注基本面良好、募投项目顺利推进的高成长性公司以及经营稳健、持续盈利能力佳的高股息率公司。",
    "id": "8WMLpi9Wf35",
    "order": 1705281674787,
    "createdAt": "2024-01-15T01:21:15.000Z",
    "publishDate": "2024-01-15T01:21:14.787Z",
    "title": "银河证券：北交所板块整体或将持续震荡行情，关注高成长性公司",
    "type": "topic",
    "up": false,
    "date": "2024-01-15 09:21:15",
    "uuid": "a7302366-e137-49aa-9180-166a49eaf8ed"
  },
  {
    "newsArray": [
      { "siteName": "凤凰科技" },
      { "siteName": "界面" },
      { "siteName": "财联社" }
    ],
    "summary": "松下能源首席技术官渡边庄一郎透露，松下将于2024年或2025年在美国内华达州工厂开始生产升级版2170电动汽车电池 ...",
    "id": "8WMKkngZ2HG",
    "order": 1705280145874,
    "createdAt": "2024-01-15T00:55:46.000Z",
    "publishDate": "2024-01-15T00:55:45.874Z",
    "title": "松下据悉最早将于2024年生产升级版电动汽车电池",
    "type": "topic",
    "up": false,
    "date": "2024-01-15 08:55:46",
    "uuid": "e69ca348-dfa9-4ebb-9979-00d5d9149cbb"
  },
  {
    "newsArray": [
      { "siteName": "36Kr" },
      { "siteName": "36Kr" },
      { "siteName": "财联社" }
    ],
    "summary": "中信建投证券研报指出，近期硅料价格暂稳，但随库存累积，2-3月价格可能下探。全年出清价格预计在5万-6万元/吨，其中N型硅料因供需紧平衡，相对P型硅料的溢价将维持，但不会成为光伏产业链瓶颈。",
    "id": "8WLLIBIQ7B5",
    "order": 1705279018302,
    "createdAt": "2024-01-15T00:36:58.000Z",
    "publishDate": "2024-01-15T00:36:58.302Z",
    "title": "中信建投：硅料价格暂企稳 供给投放较大后续可能下探",
    "type": "topic",
    "up": false,
    "date": "2024-01-15 08:36:58",
    "uuid": "cfc08f5b-1873-4689-bde4-fe974095f2e4"
  },
  {
    "newsArray": [
      { "siteName": "网易科技" },
      { "siteName": "凤凰科技" },
      { "siteName": "财联社" },
      { "siteName": "36Kr" }
    ],
    "summary": "韩国芯片制造商SK海力士计划突破美国对华的极紫外（EUV）光刻机出口限制，对中国半导体工厂进行技术升级改造，以提高制造工艺水平 ...",
    "id": "8WMIFUCASZS",
    "order": 1705278947406,
    "createdAt": "2024-01-15T00:35:47.000Z",
    "publishDate": "2024-01-15T00:35:47.406Z",
    "title": "韩国芯片巨头SK海力士计划升级在华工厂",
    "type": "topic",
    "up": false,
    "date": "2024-01-15 08:35:47",
    "uuid": "ea9fcfee-990e-42a0-a17c-a4f1b4d32098"
  },
  {
    "newsArray": [
      { "siteName": "财经网" },
      { "siteName": "证券时报网" },
      { "siteName": "新浪科技" },
      { "siteName": "澎湃新闻" }
    ],
    "summary": "多家外资机构预测2024年中国经济发展和股市投资机会，多数给出积极向好的判断。高盛、富达国际、花旗银行和瑞银证券等机构均预计2024年中国经济增长动能回升，A股市场有望受益 ...",
    "id": "8WMG7yS1XS6",
    "order": 1705281706533,
    "createdAt": "2024-01-15T00:31:53.000Z",
    "publishDate": "2024-01-15T01:21:46.533Z",
    "title": "展望2024年A股市场 多家外资机构给出积极预判",
    "type": "topic",
    "up": false,
    "date": "2024-01-15 08:31:53",
    "uuid": "59a8e2fe-a251-42ca-847e-2ed2caed722c"
  },
  {
    "newsArray": [
      { "siteName": "财联社" },
      { "siteName": "证券时报网" },
      { "siteName": "新浪科技" },
      { "siteName": "36Kr" },
      { "siteName": "36Kr" }
    ],
    "summary": "中信证券第一大股东中信金控在2023年9月4日至2024年1月11日期间，增持公司1.5亿股H股股份，增持股份数已达到公司已发行股份的1% ...",
    "id": "8WMDz0htz78",
    "order": 1705279743506,
    "createdAt": "2024-01-15T00:25:50.000Z",
    "publishDate": "2024-01-15T00:49:03.506Z",
    "title": "大股东再次增持中信证券 合计1.5亿股H股",
    "type": "topic",
    "up": false,
    "date": "2024-01-15 08:25:50",
    "uuid": "41ec6160-5d17-483b-b28d-8ade8008edea"
  },
  {
    "newsArray": [
      { "siteName": "36Kr" },
      { "siteName": "界面" },
      { "siteName": "财联社" }
    ],
    "summary": "中信建投研报称，尽管近期市场回调，但积极因素不断积累，如居民消费增长、12月CPI环比转正、房地产支持政策落地等。鉴于经济周期较长，若本周降准降息实施，有望推动市场反弹 ...",
    "id": "8WMJK39Iz8D",
    "order": 1705278303872,
    "createdAt": "2024-01-15T00:25:04.000Z",
    "publishDate": "2024-01-15T00:25:03.872Z",
    "title": "中信建投陈果：若本周降准降息落地，或推动市场反弹",
    "type": "topic",
    "up": false,
    "date": "2024-01-15 08:25:04",
    "uuid": "4d55a2da-0059-4070-989d-e8cedee9242d"
  },
  {
    "newsArray": [
      { "siteName": "网易科技" },
      { "siteName": "手机中国" },
      { "siteName": "搜狐科技" }
    ],
    "summary": "谷歌在最新版本的安卓14 QPR 2 Beta 3中添加了“搜索引擎”设置菜单，允许用户在Pixel设备中切换默认搜索引擎，如从谷歌切换至必应或DuckDuckGo ...",
    "id": "8WLUFeVGoKt",
    "order": 1705277458598,
    "createdAt": "2024-01-15T00:10:59.000Z",
    "publishDate": "2024-01-15T00:10:58.598Z",
    "title": "谷歌Pixel允许更改默认搜索引擎 或为应对反垄断诉讼",
    "type": "topic",
    "up": false,
    "date": "2024-01-15 08:10:59",
    "uuid": "e56029c8-e098-4e12-b7d6-203298fdba4c"
  },
  {
    "newsArray": [
      { "siteName": "36Kr" },
      { "siteName": "财联社" },
      { "siteName": "新浪科技" },
      { "siteName": "腾讯网" }
    ],
    "summary": "国际货币基金组织（IMF）的分析显示，人工智能（AI）将影响全球近40%的就业岗位，发达经济体受影响较大。IMF总裁格奥尔基耶娃指出，AI可能加剧贫富差距，决策者需积极应对 ...",
    "id": "8WMHY3yFHzm",
    "order": 1705279557528,
    "createdAt": "2024-01-15T00:01:25.000Z",
    "publishDate": "2024-01-15T00:45:57.528Z",
    "title": "IMF：AI将影响全球近40%就业岗位 对发达国家冲击最大",
    "type": "topic",
    "up": false,
    "date": "2024-01-15 08:01:25",
    "uuid": "6305a55f-4c87-44a2-a34d-2912e045579b"
  },
  {
    "newsArray": [
      { "siteName": "证券时报网" },
      { "siteName": "新浪科技" },
      { "siteName": "财联社" },
      { "siteName": "36Kr" }
    ],
    "summary": "2024年元旦档票房创纪录，市场关注春节档能否再创新高。截至1月14日，已有6部影片确定在春节档上映，包括《熊出没·逆转时空》、《热辣滚烫》等 ...",
    "id": "8WMGSUswTTS",
    "order": 1705276885449,
    "createdAt": "2024-01-14T23:51:39.000Z",
    "publishDate": "2024-01-15T00:01:25.449Z",
    "title": "春节档票房之争拉开帷幕 全年电影市场增长可期",
    "type": "topic",
    "up": false,
    "date": "2024-01-15 07:51:39",
    "uuid": "afa7310a-204a-454b-a324-d919edb0411c"
  },
  {
    "newsArray": [
      { "siteName": "澎湃新闻" },
      { "siteName": "新浪科技" },
      { "siteName": "新浪科技" },
      { "siteName": "新浪科技" },
      { "siteName": "财联社" },
      { "siteName": "证券时报网" }
    ],
    "summary": "近日，我国住房和城乡建设部、金融监管总局联合发布《关于建立城市房地产融资协调机制的通知》，旨在更好地支持房地产项目合理融资需求，促进房地产市场平稳健康发展 ...",
    "id": "8WMCXOQUm5g",
    "order": 1705276286065,
    "createdAt": "2024-01-14T23:41:04.000Z",
    "publishDate": "2024-01-14T23:51:26.065Z",
    "title": "两部门：建立城市房地产融资协调机制",
    "type": "topic",
    "up": false,
    "date": "2024-01-15 07:41:04",
    "uuid": "fa18c144-bc6b-46e9-a263-652f12929955"
  },
  {
    "newsArray": [
      { "siteName": "凤凰科技" },
      { "siteName": "网易科技" },
      { "siteName": "IT 之家" }
    ],
    "summary": "印度数据中心运营商 Yotta 计划向合作伙伴英伟达追加购买价值 5 亿美元的 AI 芯片，使双方订单总额提升至 10 亿美元，助力 Yotta 进一步强化其人工智能云服务能力 ...",
    "id": "8WLUEGOqp3L",
    "order": 1705272360279,
    "createdAt": "2024-01-14T22:46:00.000Z",
    "publishDate": "2024-01-14T22:46:00.279Z",
    "title": "英伟达从印度获得巨额 AI 芯片订单，价值达 5 亿美元",
    "type": "topic",
    "up": false,
    "date": "2024-01-15 06:46:00",
    "uuid": "e2ba5bbd-d6c0-4288-8028-1afc71c5803b"
  }
]
