[
  {
    "newsArray": [
      { "siteName": "36Kr" },
      { "siteName": "36Kr" },
      { "siteName": "财联社" }
    ],
    "summary": "中信证券指出，欧洲海上风电行业受政策支持、海风项目增加和融资环境改善等因素影响，预计将进入新一轮景气周期 ...",
    "id": "8b4RpinOGo2",
    "order": 1720489387549,
    "createdAt": "2024-07-09T01:43:07.000Z",
    "publishDate": "2024-07-09T01:43:07.549Z",
    "title": "中信证券：欧洲海上风电或开启新一轮景气周期",
    "type": "topic",
    "up": false,
    "date": "2024-07-09 09:43:07",
    "uuid": "b8017cf6-eaa1-41db-a2d8-a5ebb6d1855f"
  },
  {
    "newsArray": [
      { "siteName": "爱范儿" },
      { "siteName": "IT 之家" },
      { "siteName": "品玩" }
    ],
    "summary": "Kimi浏览器插件推出了两项新功能：点问笔和总结器。点问笔能在用户划选文字后提供更深入的上下文理解，而总结器能快速总结当前网页全文内容 ...",
    "id": "8b30A6HX5X9",
    "order": 1720489256768,
    "createdAt": "2024-07-09T01:40:56.000Z",
    "publishDate": "2024-07-09T01:40:56.768Z",
    "title": "月之暗面推出 Kimi 浏览器插件，增加多项新功能",
    "type": "topic",
    "up": false,
    "date": "2024-07-09 09:40:56",
    "uuid": "55fc105e-3d12-4dbd-a7a1-02fce75579fb"
  },
  {
    "newsArray": [
      { "siteName": "证券时报网" },
      { "siteName": "证券时报网" },
      { "siteName": "证券时报网" },
      { "siteName": "和讯网" }
    ],
    "summary": "上证指数昨日下跌0.93%，北向资金成交1060.12亿元，净卖出22.00亿元。陆股通共持有3346只个股，增持的有973只，减持的有1957只 ...",
    "id": "8b4TeJSmyzc",
    "order": 1720488733177,
    "createdAt": "2024-07-09T01:32:13.000Z",
    "publishDate": "2024-07-09T01:32:13.177Z",
    "title": "北向资金增仓榜：60股持股量环比增加超50%",
    "type": "topic",
    "up": false,
    "date": "2024-07-09 09:32:13",
    "uuid": "8163f892-8866-4b3d-b9b7-b51c3820bf46"
  },
  {
    "newsArray": [
      { "siteName": "新浪科技" },
      { "siteName": "36Kr" },
      { "siteName": "财联社" },
      { "siteName": "界面" }
    ],
    "summary": "7月9日，多只中报预增概念股表现强势，如鲁北化工、中孚实业等涨停，富瑞特装、西陇科学等高开 ...",
    "id": "8b4Vm7iY90g",
    "order": 1720488722795,
    "createdAt": "2024-07-09T01:32:02.000Z",
    "publishDate": "2024-07-09T01:32:02.795Z",
    "title": "中报预增概念股逆势大涨，鲁北化工竞价涨停",
    "type": "topic",
    "up": false,
    "date": "2024-07-09 09:32:02",
    "uuid": "9a9513f0-c55a-4aa5-b4db-56166753a1ae"
  },
  {
    "newsArray": [
      { "siteName": "IT 之家" },
      { "siteName": "和讯网" },
      { "siteName": "财联社" }
    ],
    "summary": "苹果公司正考虑在印度生产iPad产品线，得益于印度政府计划推出的新奖励和扶持政策。此前苹果曾计划与比亚迪合作在印生产iPad，但审批过程面临挑战 ...",
    "id": "8b35rZuiAmL",
    "order": 1720488667441,
    "createdAt": "2024-07-09T01:31:08.000Z",
    "publishDate": "2024-07-09T01:31:07.441Z",
    "title": "苹果被曝重启在印度生产 iPad 计划，未来还将拓展至 Mac 产品线",
    "type": "topic",
    "up": false,
    "date": "2024-07-09 09:31:08",
    "uuid": "2dba9d24-f944-4e7e-af23-bdd6d42cc5e1"
  },
  {
    "newsArray": [
      { "siteName": "财经网" },
      { "siteName": "36Kr" },
      { "siteName": "新浪科技" },
      { "siteName": "36Kr" }
    ],
    "summary": "中国人民银行宣布启动临时正回购和逆回购操作，以保持银行体系流动性合理充裕，并提高公开市场操作的精准性和有效性。这一新操作将与其他货币政策工具共同作用，更及时地调节市场流动性 ...",
    "id": "8b4LnCLt1gJ",
    "order": 1720489017781,
    "createdAt": "2024-07-09T01:21:46.000Z",
    "publishDate": "2024-07-09T01:36:57.781Z",
    "title": "精准调节流动性 央行创设临时隔夜正、逆回购操作",
    "type": "topic",
    "up": false,
    "date": "2024-07-09 09:21:46",
    "uuid": "0dcca471-15d2-4d7a-ae99-b40cc8468ae9"
  },
  {
    "newsArray": [
      { "siteName": "36Kr" },
      { "siteName": "财联社" },
      { "siteName": "智通财经" }
    ],
    "summary": "2024年上半年，我国房地产融资政策主要聚焦于银行信贷端，发挥“白名单”和经营性物业贷作用，以满足开发项目的合理融资需求 ...",
    "id": "8b4NvfTJixJ",
    "order": 1720485414072,
    "createdAt": "2024-07-09T00:36:55.000Z",
    "publishDate": "2024-07-09T00:36:54.072Z",
    "title": "中指研究院：上半年房地产融资规模仍在下降 白名单机制成果显现",
    "type": "topic",
    "up": false,
    "date": "2024-07-09 08:36:55",
    "uuid": "1e605ac4-1bdf-45ad-9b9d-31ceb1541c6a"
  },
  {
    "newsArray": [
      { "siteName": "财联社" },
      { "siteName": "搜狐科技" },
      { "siteName": "IT 之家" }
    ],
    "summary": "苹果即将推出的“Apple Intelligence”功能将首先适用于iPhone、iPad和Mac设备，而HomePod、Apple Watch和Vision Pro等产品将暂时无法使用该功能，包括新版Siri语音助手 ...",
    "id": "8b3oBe68b2a",
    "order": 1720485343361,
    "createdAt": "2024-07-09T00:35:43.000Z",
    "publishDate": "2024-07-09T00:35:43.361Z",
    "title": "苹果首款支持Apple Intelligence的智能家居设备将是桌面机器人",
    "type": "topic",
    "up": false,
    "date": "2024-07-09 08:35:43",
    "uuid": "d2bb6b6d-2b38-4b29-9a28-ee509bd8ff03"
  },
  {
    "newsArray": [
      { "siteName": "界面" },
      { "siteName": "智通财经" },
      { "siteName": "财联社" },
      { "siteName": "36Kr" }
    ],
    "summary": "快手宣布，根据之前披露的160亿港元股份购回计划，已与独立经纪商签订购回合约，将在香港联交所购回最多60亿港元的B类普通股。",
    "id": "8b4QcyhJTp4",
    "order": 1720485049856,
    "createdAt": "2024-07-09T00:30:49.000Z",
    "publishDate": "2024-07-09T00:30:49.856Z",
    "title": "快手：将购回不超过60亿港元公司B类股",
    "type": "topic",
    "up": false,
    "date": "2024-07-09 08:30:49",
    "uuid": "ccac169e-7209-4f5b-acb2-13c674245539"
  },
  {
    "newsArray": [
      { "siteName": "36Kr" },
      { "siteName": "界面" },
      { "siteName": "新浪科技" },
      { "siteName": "证券时报网" }
    ],
    "summary": "文章分析了2024年以来，我国有色金属、化工、生猪养殖等行业产品价格的上涨情况，指出这不仅预示着行业回暖，也为相关上市公司业绩增长提供了动力 ...",
    "id": "8b4MUht4t8C",
    "order": 1720488715093,
    "createdAt": "2024-07-09T00:19:13.000Z",
    "publishDate": "2024-07-09T01:31:55.093Z",
    "title": "暖意渐浓 多个行业赛道“涨”声不断",
    "type": "topic",
    "up": false,
    "date": "2024-07-09 08:19:13",
    "uuid": "aa699cf3-be60-4967-8746-6478a45f7f33"
  },
  {
    "newsArray": [
      { "siteName": "36Kr" },
      { "siteName": "新浪科技" },
      { "siteName": "财联社" },
      { "siteName": "界面" }
    ],
    "summary": "中信建投认为，消费税改革可能会增强免税渠道的价格优势，尤其是对于高档产品，这可能会加大免税与其他销售渠道之间的价差 ...",
    "id": "8b4PLFG9hD7",
    "order": 1720485080024,
    "createdAt": "2024-07-09T00:19:03.000Z",
    "publishDate": "2024-07-09T00:31:20.024Z",
    "title": "中信建投：消费税潜在改革 有望利好免税价差",
    "type": "topic",
    "up": false,
    "date": "2024-07-09 08:19:03",
    "uuid": "a8a4adeb-e749-44d8-9e19-d27202e1a7e5"
  },
  {
    "newsArray": [
      { "siteName": "36Kr" },
      { "siteName": "界面" },
      { "siteName": "证券时报网" }
    ],
    "summary": "根据Wind数据，截至7月8日，今年已有1078家A股上市公司采取各种措施提升盈利和分红能力，如聚焦主业、布局新赛道、调整资产结构等，以增强资本市场的内在稳定性。",
    "id": "8b4OebUoaSh",
    "order": 1720484333392,
    "createdAt": "2024-07-09T00:18:54.000Z",
    "publishDate": "2024-07-09T00:18:53.392Z",
    "title": "A股公司“千方百计”提升盈利与分红能力",
    "type": "topic",
    "up": false,
    "date": "2024-07-09 08:18:54",
    "uuid": "232513a9-4ce6-415b-b4f1-f342749090a7"
  },
  {
    "newsArray": [
      { "siteName": "界面" },
      { "siteName": "36Kr" },
      { "siteName": "财联社" }
    ],
    "summary": "华泰证券报告指出，受新能源需求和传统领域复苏推动，氧化镨钕需求在过去几年迅速增长，预计2023至2026年需求复合年增速达10.8% ...",
    "id": "8b4NuorZ5Hl",
    "order": 1720483930442,
    "createdAt": "2024-07-09T00:12:10.000Z",
    "publishDate": "2024-07-09T00:12:10.442Z",
    "title": "华泰证券：稀土价格短期寻底，长期供需改善",
    "type": "topic",
    "up": false,
    "date": "2024-07-09 08:12:10",
    "uuid": "393c1590-bff2-41d3-b6ff-f9c33d40ff82"
  },
  {
    "newsArray": [
      { "siteName": "和讯网" },
      { "siteName": "财联社" },
      { "siteName": "财联社" }
    ],
    "summary": "中央气象台发布暴雨黄色预警，预计7月9日08时至10日08时，陕西南部、四川盆地中北部和西部、湖北西部和东北部、河南东南部、安徽中北部、江苏中部以及云南西北部等地有大到暴雨，局部地区有大暴雨 ...",
    "id": "8b4HT9Fj99m",
    "order": 1720483281294,
    "createdAt": "2024-07-09T00:01:21.000Z",
    "publishDate": "2024-07-09T00:01:21.294Z",
    "title": "中央气象台7月9日06时发布暴雨黄色预警",
    "type": "topic",
    "up": false,
    "date": "2024-07-09 08:01:21",
    "uuid": "3a362516-bfd8-4e70-83bf-a4b04851082b"
  },
  {
    "newsArray": [
      { "siteName": "证券时报网" },
      { "siteName": "界面" },
      { "siteName": "财联社" }
    ],
    "summary": "沪深两市ETF规模接近2.5万亿元，其中沪市ETF总市值为18449.98亿元，深市ETF总市值为6044.45亿元 ...",
    "id": "8b4JyK8CF5z",
    "order": 1720482142679,
    "createdAt": "2024-07-08T23:42:22.000Z",
    "publishDate": "2024-07-08T23:42:22.679Z",
    "title": "沪深ETF规模近2.5万亿元 市场波动中券商代销优势显现",
    "type": "topic",
    "up": false,
    "date": "2024-07-09 07:42:22",
    "uuid": "fa5af8d2-e39d-47cd-a22a-45c97f5597d2"
  },
  {
    "newsArray": [
      { "siteName": "新浪科技" },
      { "siteName": "36Kr" },
      { "siteName": "新浪科技" },
      { "siteName": "36Kr" },
      { "siteName": "证券时报网" }
    ],
    "summary": "国务院办公厅最近发布了《促进创业投资高质量发展的若干政策措施》（简称“创投十七条”），其中第五部分重点关注创业投资退出机制的完善 ...",
    "id": "8b4Lmv1VIM3",
    "order": 1720488085574,
    "createdAt": "2024-07-08T23:41:12.000Z",
    "publishDate": "2024-07-09T01:21:25.574Z",
    "title": "机构呼吁拓展多元化退出渠道 促进一级市场投资再循环",
    "type": "topic",
    "up": false,
    "date": "2024-07-09 07:41:12",
    "uuid": "d4b1938f-38a6-43ef-a63c-546285b9b584"
  },
  {
    "newsArray": [
      { "siteName": "36Kr" },
      { "siteName": "新浪科技" },
      { "siteName": "财联社" },
      { "siteName": "证券时报网" }
    ],
    "summary": "国债期货近日全线下跌，央行宣布将视情况开展临时正回购或临时逆回购操作，以提高调控资金面的精准性和有效性 ...",
    "id": "8b4CSxcO3sU",
    "order": 1720482076297,
    "createdAt": "2024-07-08T23:36:52.000Z",
    "publishDate": "2024-07-08T23:41:16.297Z",
    "title": "债市深度回调 分析人士提醒债券投资谨慎为上",
    "type": "topic",
    "up": false,
    "date": "2024-07-09 07:36:52",
    "uuid": "d4217a5f-1876-4398-9823-cf7c1c7a6cf1"
  },
  {
    "newsArray": [
      { "siteName": "36Kr" },
      { "siteName": "IT 之家" },
      { "siteName": "财联社" }
    ],
    "summary": "梅赛德斯-奔驰将在德国斯图加特总部建立电池研发中心，投入数亿欧元用于开发新型化学组合和优化制造工艺，旨在未来几年内将电池成本降低30%以上。该中心还将负责生产电池并进行测试。",
    "id": "8b3fxrVYU4s",
    "order": 1720480369999,
    "createdAt": "2024-07-08T23:12:49.000Z",
    "publishDate": "2024-07-08T23:12:49.999Z",
    "title": "梅赛德斯-奔驰将在德国总部开设研发中心，目标削减30%以上电池成本",
    "type": "topic",
    "up": false,
    "date": "2024-07-09 07:12:49",
    "uuid": "c114bcd9-9b3e-4580-9477-d603fe5b8c6b"
  },
  {
    "newsArray": [
      { "siteName": "界面" },
      { "siteName": "36Kr" },
      { "siteName": "财联社" }
    ],
    "summary": "7月8日，美股三大指数收盘表现不一，道指微跌，纳指和标普500指数小幅上涨。大型科技股中，苹果股价上涨，市值逼近3.5万亿美元，领跑市值榜 ...",
    "id": "8b48XCSlzLj",
    "order": 1720480266822,
    "createdAt": "2024-07-08T23:11:06.000Z",
    "publishDate": "2024-07-08T23:11:06.822Z",
    "title": "美股三大指数收盘涨跌不一，热门中概股普跌",
    "type": "topic",
    "up": false,
    "date": "2024-07-09 07:11:06",
    "uuid": "e0da9ee8-b7bd-416d-9b95-b27869b5189c"
  },
  {
    "newsArray": [
      { "siteName": "新浪科技" },
      { "siteName": "IT 之家" },
      { "siteName": "智通财经" },
      { "siteName": "36Kr" }
    ],
    "summary": "派拉蒙环球公司宣布与David Ellison的Skydance Media合并，此交易已获得特别委员会的一致批准 ...",
    "id": "8b2uSMDK3XD",
    "order": 1720484681215,
    "createdAt": "2024-07-08T20:41:19.000Z",
    "publishDate": "2024-07-09T00:24:41.215Z",
    "title": "又一桩撼动好莱坞版图交易，派拉蒙宣布与 Skydance 合并",
    "type": "topic",
    "up": false,
    "date": "2024-07-09 04:41:19",
    "uuid": "dd88f70d-1f1d-4268-9071-70687b0c2c27"
  },
  {
    "newsArray": [
      { "siteName": "新浪科技" },
      { "siteName": "华尔街见闻" },
      { "siteName": "财联社" },
      { "siteName": "新浪科技" },
      { "siteName": "界面" },
      { "siteName": "36Kr" },
      { "siteName": "IT 之家" }
    ],
    "summary": "美国联合航空公司一架波音757-200飞机在起飞时丢失了一个主起落架轮胎，所幸无人受伤 ...",
    "id": "8b476ZMUVVg",
    "order": 1720481799622,
    "createdAt": "2024-07-08T20:10:54.000Z",
    "publishDate": "2024-07-08T23:36:39.622Z",
    "title": "美联航3月事故重演 一架波音飞机起飞后轮胎掉落",
    "type": "topic",
    "up": false,
    "date": "2024-07-09 04:10:54",
    "uuid": "991591bd-b694-47a2-bdf4-245f30564fae"
  },
  {
    "newsArray": [
      { "siteName": "搜狐科技" },
      { "siteName": "华尔街见闻" },
      { "siteName": "搜狐科技" }
    ],
    "summary": "半导体存储芯片领域中，人工智能AI成为推动厂商业绩增长的重要因素。三星电子第二季度营业利润激增近15倍，远超市场预期，主要得益于全球半导体市场回暖和AI热潮带动的存储芯片需求复苏 ...",
    "id": "8b3OSb0aWFN",
    "order": 1720466456193,
    "createdAt": "2024-07-08T19:20:56.000Z",
    "publishDate": "2024-07-08T19:20:56.193Z",
    "title": "半导体存储厂商“各显神通”",
    "type": "topic",
    "up": false,
    "date": "2024-07-09 03:20:56",
    "uuid": "01d1b366-25be-4bc3-996e-abba1ec18978"
  },
  {
    "newsArray": [
      { "siteName": "IT 之家" },
      { "siteName": "IT 之家" },
      { "siteName": "IT 之家" },
      { "siteName": "快科技" }
    ],
    "summary": "苹果发布了visionOS 2开发者预览版Beta 3更新，内部版本号为22N5277g，距离上次发布14天。由于苹果服务器配置缓存问题，更新可能会有延迟，但通常不会超过半小时 ...",
    "id": "8b40KYYarUd",
    "order": 1720478924375,
    "createdAt": "2024-07-08T18:10:55.000Z",
    "publishDate": "2024-07-08T22:48:44.375Z",
    "title": "苹果 visionOS 2 开发者预览版 Beta 3 发布",
    "type": "topic",
    "up": false,
    "date": "2024-07-09 02:10:55",
    "uuid": "4128c627-fec7-484d-aade-b93b589efdd0"
  }
]
