[
  {
    "newsArray": [
      { "siteName": "格隆汇" },
      { "siteName": "快科技" },
      { "siteName": "IT 之家" },
      { "siteName": "华尔街见闻" },
      { "siteName": "界面" }
    ],
    "summary": "2025年11月1日晚奇瑞集团公布，10月销售汽车281,161辆，同比增长3.3%，其中新能源汽车销售110,346辆，同比增长54.7%，首次单月超11万辆，出口126,434辆，同比增长13% ...",
    "id": "8nw2XWslMwp",
    "order": 1762045344614,
    "createdAt": "2025-11-02T01:02:24.000Z",
    "publishDate": "2025-11-02T01:02:24.614Z",
    "title": "奇瑞集团10月汽车销量28.1万辆 同比增长3.3%",
    "type": "topic",
    "up": false,
    "date": "2025-11-02 09:02:24",
    "uuid": "c23d13f5-50d8-4fd1-a4cf-33b4d86a6aec"
  },
  {
    "newsArray": [
      { "siteName": "华尔街见闻" },
      { "siteName": "格隆汇" },
      { "siteName": "格隆汇" },
      { "siteName": "第一财经" },
      { "siteName": "财联社" },
      { "siteName": "界面" }
    ],
    "summary": "俄罗斯地区行政管理部门称，乌克兰无人机袭击俄黑海港口图阿普谢，一艘油轮受损。",
    "id": "8nwhGj952T6",
    "order": 1762044739629,
    "createdAt": "2025-11-02T00:52:19.000Z",
    "publishDate": "2025-11-02T00:52:19.629Z",
    "title": "俄方称乌克兰无人机袭击港口图阿普谢 一艘油轮受损",
    "type": "topic",
    "up": false,
    "date": "2025-11-02 08:52:19",
    "uuid": "e06ff078-29d2-4d62-a20e-8aeaa89c3d33"
  },
  {
    "newsArray": [
      { "siteName": "界面" },
      { "siteName": "格隆汇" },
      { "siteName": "财联社" },
      { "siteName": "华尔街见闻" }
    ],
    "summary": "10月31日，首期江苏社保科创基金正式签约落地苏州，江苏省委书记信长星、省长刘小涛等见证合伙协议签署并揭牌 ...",
    "id": "8nwla6rD7RJ",
    "order": 1762043565417,
    "createdAt": "2025-11-02T00:32:45.000Z",
    "publishDate": "2025-11-02T00:32:45.417Z",
    "title": "江苏社保科创基金正式成立",
    "type": "topic",
    "up": false,
    "date": "2025-11-02 08:32:45",
    "uuid": "a9e06efc-509d-4110-a249-e8099a7a2063"
  },
  {
    "newsArray": [
      { "siteName": "格隆汇" },
      { "siteName": "第一财经" },
      { "siteName": "华尔街见闻" }
    ],
    "summary": "安利股份在接受机构调研时称，半导体领域首批小批量订单量产交付，客户反馈好，但订单金额小，短期内对营收无重大影响，后续将积极拓展客户，探索新增长点。",
    "id": "8nwlbIxw3ve",
    "order": 1762043508593,
    "createdAt": "2025-11-02T00:31:49.000Z",
    "publishDate": "2025-11-02T00:31:48.593Z",
    "title": "安利股份：半导体领域首批小批量订单量产交付后客户反馈较好",
    "type": "topic",
    "up": false,
    "date": "2025-11-02 08:31:49",
    "uuid": "4d36dedd-550b-4e48-a67d-163ffcc9523b"
  },
  {
    "newsArray": [
      { "siteName": "华尔街见闻" },
      { "siteName": "财联社" },
      { "siteName": "第一财经" },
      { "siteName": "格隆汇" }
    ],
    "summary": "安利股份在接受机构调研时称，市场上针对具身智能场景的聚氨酯复合材料未形成成熟可行的规模化技术方案与成品，行业处于技术探索阶段 ...",
    "id": "8nwkyMNPhFA",
    "order": 1762042932336,
    "createdAt": "2025-11-02T00:22:12.000Z",
    "publishDate": "2025-11-02T00:22:12.336Z",
    "title": "安利股份：公司针对具身智能场景的聚氨酯复合材料开发处于初期探索阶段",
    "type": "topic",
    "up": false,
    "date": "2025-11-02 08:22:12",
    "uuid": "fa174f83-fb67-46fd-8268-7899e121794b"
  },
  {
    "newsArray": [
      { "siteName": "网易科技" },
      { "siteName": "凤凰科技" },
      { "siteName": "IT 之家" }
    ],
    "summary": "百度“文心一言”App 于 2023 年 7 月 4 日上架 App Store，2024 年 9 月 4 日发布 4.0.0 版本并改为“文小言”，现发布 5.0.0 版本，名称再次改为“文心” ...",
    "id": "8nw9hy3D9T7",
    "order": 1762042897659,
    "createdAt": "2025-11-02T00:21:37.000Z",
    "publishDate": "2025-11-02T00:21:37.659Z",
    "title": "百度文小言5.0版本再次改名为“文心”",
    "type": "topic",
    "up": false,
    "date": "2025-11-02 08:21:37",
    "uuid": "d756eb4a-8fff-472c-9349-c699808614c9"
  },
  {
    "newsArray": [
      { "siteName": "华尔街见闻" },
      { "siteName": "财联社" },
      { "siteName": "格隆汇" },
      { "siteName": "第一财经" },
      { "siteName": "钛媒体" }
    ],
    "summary": "当地时间11月1日，美国民间组织全国家长联盟称，数百万人的“补充营养援助计划”（SNAP）福利因“余额不足”失效，数百万该计划用户当日未收到福利金，约4200万美国人依靠该计划购买食物。",
    "id": "8nwjQEiJ3l4",
    "order": 1762041793555,
    "createdAt": "2025-11-02T00:03:13.000Z",
    "publishDate": "2025-11-02T00:03:13.555Z",
    "title": "“余额不足” 美数百万人已无法领取食品援助福利金",
    "type": "topic",
    "up": false,
    "date": "2025-11-02 08:03:13",
    "uuid": "25b92775-0e5e-4ad7-8af5-7bd7a1feeb14"
  },
  {
    "newsArray": [
      { "siteName": "IT 之家" },
      { "siteName": "凤凰科技" },
      { "siteName": "快科技" }
    ],
    "summary": "FF旗下FX品牌首款车型FX Super One在迪拜全球首发，贾跃亭称其市场表现亮眼，上市48小时获200 + B2B付费预订单，足球巨星伊涅斯塔成为全球首位车主兼开发者共创官 ...",
    "id": "8nvXX3NZti7",
    "order": 1762041761181,
    "createdAt": "2025-11-02T00:02:41.000Z",
    "publishDate": "2025-11-02T00:02:41.181Z",
    "title": "贾跃亭新车48小时斩获200+预订单 足球巨星伊涅斯塔成首位车主",
    "type": "topic",
    "up": false,
    "date": "2025-11-02 08:02:41",
    "uuid": "c22af17f-8292-4bcb-a02f-425cfd2c6b43"
  },
  {
    "newsArray": [
      { "siteName": "科学网" },
      { "siteName": "格隆汇" },
      { "siteName": "财联社" }
    ],
    "summary": "当地时间11月1日凌晨3点前不久，美国哈佛医学院一栋位于朗伍德校区主广场戈尔登森大楼四楼的建筑发生爆炸 ...",
    "id": "8nwT2P5YzIL",
    "order": 1762040794754,
    "createdAt": "2025-11-01T23:46:34.000Z",
    "publishDate": "2025-11-01T23:46:34.754Z",
    "title": "美国哈佛医学院一建筑发生爆炸 疑似蓄意所为",
    "type": "topic",
    "up": false,
    "date": "2025-11-02 07:46:34",
    "uuid": "fb2d5d44-87ce-49bb-b430-ff3662f48492"
  },
  {
    "newsArray": [
      { "siteName": "格隆汇" },
      { "siteName": "财联社" },
      { "siteName": "新浪科技" },
      { "siteName": "华尔街见闻" }
    ],
    "summary": "据三位不愿具名代表透露，在周日线上会议前，欧佩克+成员国倾向于12月再次小幅提高石油产量，组织核心成员国正讨论日产量提高约13.7万桶，与10月和11月调整幅度一致，相关讨论将在周日继续 ...",
    "id": "8nwQCMK2dpF",
    "order": 1762042285459,
    "createdAt": "2025-11-01T23:42:05.000Z",
    "publishDate": "2025-11-02T00:11:25.459Z",
    "title": "欧佩克+讨论聚焦12月小幅提高石油产量",
    "type": "topic",
    "up": false,
    "date": "2025-11-02 07:42:05",
    "uuid": "88ca725d-5a76-4980-b297-5fd67911a0b9"
  },
  {
    "newsArray": [
      { "siteName": "界面" },
      { "siteName": "格隆汇" },
      { "siteName": "财联社" }
    ],
    "summary": "当地时间11月1日，英国一列前往剑桥郡亨廷顿的火车上发生持刀行凶事件，伤亡情况不明，已有两人被警方逮捕，英国交通警察和剑桥郡警方正在应对。",
    "id": "8nwbjN7rLNS",
    "order": 1762038159255,
    "createdAt": "2025-11-01T23:02:40.000Z",
    "publishDate": "2025-11-01T23:02:39.255Z",
    "title": "英国一火车发生持刀行凶事件 已有2人被捕",
    "type": "topic",
    "up": false,
    "date": "2025-11-02 07:02:40",
    "uuid": "cafcd2a6-12ad-43ae-94cb-6cec1b470a17"
  },
  {
    "newsArray": [
      { "siteName": "格隆汇" },
      { "siteName": "财联社" },
      { "siteName": "财联社" }
    ],
    "summary": "当地时间11月1日下午，德国法兰克福西北城区的西北城购物中心有顾客听到至少一声巨响，疑似发生枪击事件。许多顾客逃离商场，部分被引导从紧急出口离开，购物中心自下午起被封锁 ...",
    "id": "8nwGE4zfezn",
    "order": 1762035075022,
    "createdAt": "2025-11-01T22:11:15.000Z",
    "publishDate": "2025-11-01T22:11:15.022Z",
    "title": "德国法兰克福一购物中心传出巨响 疑似发生枪击事件",
    "type": "topic",
    "up": false,
    "date": "2025-11-02 06:11:15",
    "uuid": "308ee07b-2793-47ea-b295-6f58f738de25"
  }
]
