[
  {
    "newsArray": [
      { "siteName": "格隆汇" },
      { "siteName": "格隆汇" },
      { "siteName": "华尔街见闻" }
    ],
    "summary": "WTI 9月原油期货收跌1.06%，报69.26美元/桶，但7月累计上涨超过8.47%。中东Abu Dhabi Murban原油期货7月累计上涨10.88%，近期加速上涨至73.86美元/桶 ...",
    "id": "8lS1HBnfKEl",
    "order": 1754000556317,
    "createdAt": "2025-07-31T22:22:37.000Z",
    "publishDate": "2025-07-31T22:22:36.317Z",
    "title": "美国原油期货7月份涨约8.5%，纽约天然气累跌11%",
    "type": "topic",
    "up": false,
    "date": "2025-08-01 06:22:37",
    "uuid": "7ef9b123-065c-4ee9-87b3-277d690f1835"
  },
  {
    "newsArray": [
      { "siteName": "格隆汇" },
      { "siteName": "凤凰科技" },
      { "siteName": "格隆汇" },
      { "siteName": "新浪科技" }
    ],
    "summary": "亚马逊发布2025财年第二季度财报，总营收达1677.02亿美元，同比增长13%。净利润为181.64亿美元，同比增长35% ...",
    "id": "8lS94XCjeYB",
    "order": 1754000526645,
    "createdAt": "2025-07-31T22:22:06.000Z",
    "publishDate": "2025-07-31T22:22:06.645Z",
    "title": "亚马逊第二季度净利润增长35% 展望不佳股价大跌近6%",
    "type": "topic",
    "up": false,
    "date": "2025-08-01 06:22:06",
    "uuid": "c74f105a-805a-41b0-831e-328febde58a0"
  },
  {
    "newsArray": [
      { "siteName": "华尔街见闻" },
      { "siteName": "格隆汇" },
      { "siteName": "华尔街见闻" }
    ],
    "summary": "苹果公司季度总收入增长10%，为2021年12月以来最大增幅。CEO库克表示将大幅增加人工智能投资，并考虑通过并购加速发展 ...",
    "id": "8lSAWXYdjUc",
    "order": 1753996315969,
    "createdAt": "2025-07-31T21:11:55.000Z",
    "publishDate": "2025-07-31T21:11:55.969Z",
    "title": "苹果季度收入增幅创2021年年底以来最大，库克：将大幅增加AI投资",
    "type": "topic",
    "up": false,
    "date": "2025-08-01 05:11:55",
    "uuid": "2ecc6a49-8591-442a-9d39-baf37b03f84c"
  },
  {
    "newsArray": [
      { "siteName": "华尔街见闻" },
      { "siteName": "财联社" },
      { "siteName": "新浪科技" },
      { "siteName": "格隆汇" }
    ],
    "summary": "美股周四午盘涨跌不一，纳指与标普500创盘中新高，微软与Meta的强劲财报提振市场情绪。特朗普发布新关税措施，但其合法性将面临司法挑战 ...",
    "id": "8lRqhUTjsVS",
    "order": 1753999851236,
    "createdAt": "2025-07-31T20:32:32.000Z",
    "publishDate": "2025-07-31T22:10:51.236Z",
    "title": "午盘：美股涨跌不一 微软与Meta推动科技股走高",
    "type": "topic",
    "up": false,
    "date": "2025-08-01 04:32:32",
    "uuid": "b6b07de1-b021-47a1-94d4-8a0c4737f014"
  },
  {
    "newsArray": [
      { "siteName": "awtmt.com_news" },
      { "siteName": "华尔街见闻" },
      { "siteName": "华尔街见闻" }
    ],
    "summary": "亚马逊二季度净销售额达1677.0亿美元，超出预期的1621.5亿美元，AWS业务净销售额同比增长17%，符合市场预期。",
    "id": "8lS729mai3w",
    "order": 1753995482480,
    "createdAt": "2025-07-31T20:16:11.000Z",
    "publishDate": "2025-07-31T20:58:02.480Z",
    "title": "亚马逊二季度净销售 1677.0 亿美元，预期 1621.5 亿美元",
    "type": "topic",
    "up": false,
    "date": "2025-08-01 04:16:11",
    "uuid": "2c6c06c8-8597-4402-8981-0a686824156c"
  },
  {
    "newsArray": [
      { "siteName": "华尔街见闻" },
      { "siteName": "awtmt.com_news" },
      { "siteName": "华尔街见闻" }
    ],
    "summary": "Figma公司美国IPO首日开盘价为85美元，发行价为每股33美元。",
    "id": "8lRyOay7uzO",
    "order": 1753992213955,
    "createdAt": "2025-07-31T20:03:33.000Z",
    "publishDate": "2025-07-31T20:03:33.955Z",
    "title": "Figma美国IPO首日高开超157%",
    "type": "topic",
    "up": false,
    "date": "2025-08-01 04:03:33",
    "uuid": "f739c9c7-2940-4309-8aa0-284babe58e67"
  },
  {
    "newsArray": [
      { "siteName": "财联社" },
      { "siteName": "华尔街见闻" },
      { "siteName": "格隆汇" }
    ],
    "summary": "俄军在2025年7月以每天300-400架的规模，向乌克兰各地目标发射了6297架无人机，是2024年同期的14.7倍，超过2024年全年总和，这也是俄军首次在一个月内向乌军目标发射超过6000架无人机。",
    "id": "8lS5UcEVybv",
    "order": 1753992181146,
    "createdAt": "2025-07-31T20:03:01.000Z",
    "publishDate": "2025-07-31T20:03:01.146Z",
    "title": "俄军七月向乌发射6000余架无人机 超2024年全年总和",
    "type": "topic",
    "up": false,
    "date": "2025-08-01 04:03:01",
    "uuid": "8e6616c1-abbe-443b-8727-27645bdb1d18"
  },
  {
    "newsArray": [
      { "siteName": "华尔街见闻" },
      { "siteName": "财联社" },
      { "siteName": "财联社" },
      { "siteName": "第一财经" }
    ],
    "summary": "俄罗斯对基辅发动的夜间导弹和无人机袭击已造成11人死亡，乌克兰基辅市长在社交媒体上发布了这一消息，而俄方尚未对此作出回应。",
    "id": "8lRkcnJ11dI",
    "order": 1753990330783,
    "createdAt": "2025-07-31T19:32:10.000Z",
    "publishDate": "2025-07-31T19:32:10.783Z",
    "title": "乌称俄导弹和无人机袭击已致基辅11人死亡",
    "type": "topic",
    "up": false,
    "date": "2025-08-01 03:32:10",
    "uuid": "c0df18d0-e6f0-48df-80b6-de5b8dcd4a51"
  },
  {
    "newsArray": [
      { "siteName": "华尔街见闻" },
      { "siteName": "财联社" },
      { "siteName": "格隆汇" }
    ],
    "summary": "摘要：俄罗斯堪察加半岛阿瓦恰湾海域7月30日发生8.7级强震，随后监测到约1000次余震。当地专家认为，此次强震可能标志着该地区一年多来地震活动的结束。",
    "id": "8lS1uji9hGk",
    "order": 1753989156646,
    "createdAt": "2025-07-31T19:12:36.000Z",
    "publishDate": "2025-07-31T19:12:36.646Z",
    "title": "俄地震部门：堪察加半岛近海强震后测到约千次余震",
    "type": "topic",
    "up": false,
    "date": "2025-08-01 03:12:36",
    "uuid": "6036813c-6ca3-4775-96f4-56efd70dd994"
  },
  {
    "newsArray": [
      { "siteName": "华尔街见闻" },
      { "siteName": "财联社" },
      { "siteName": "格隆汇" }
    ],
    "summary": "2025年第一季度全球服务贸易增速放缓至5%，较2024年和2023年同期水平下降一半。欧洲和北美服务贸易出口增长仅为3%，低于2024年同期数据，而亚洲则保持9%的强劲增长 ...",
    "id": "8lS3L1wv7Mw",
    "order": 1753989139033,
    "createdAt": "2025-07-31T19:12:20.000Z",
    "publishDate": "2025-07-31T19:12:19.033Z",
    "title": "世贸组织：2025年第一季度服务贸易增长放缓",
    "type": "topic",
    "up": false,
    "date": "2025-08-01 03:12:20",
    "uuid": "abf60448-e4ab-4e9e-bd96-b25af8dd2bfa"
  },
  {
    "newsArray": [
      { "siteName": "格隆汇" },
      { "siteName": "华尔街见闻" },
      { "siteName": "格隆汇" },
      { "siteName": "财联社" }
    ],
    "summary": "设计软件公司Figma股价大幅上涨，涨幅达229%。",
    "id": "8lRyKlwDVj4",
    "order": 1753995525325,
    "createdAt": "2025-07-31T18:11:17.000Z",
    "publishDate": "2025-07-31T20:58:45.325Z",
    "title": "设计软件巨头 Figma 涨幅扩大至 229%",
    "type": "topic",
    "up": false,
    "date": "2025-08-01 02:11:17",
    "uuid": "085bc6f4-a961-4e89-8b48-12ea68631d00"
  },
  {
    "newsArray": [
      { "siteName": "牛透社" },
      { "siteName": "IT 之家" },
      { "siteName": "界面" }
    ],
    "summary": "人工智能企业阶跃星辰发布新一代基础大模型 Step 3，参数量达 3210 亿，具备强智能、高效率、可开源和多模态特性 ...",
    "id": "8lRhIcL66o3",
    "order": 1753980938856,
    "createdAt": "2025-07-31T16:55:41.000Z",
    "publishDate": "2025-07-31T16:55:38.856Z",
    "title": "阶跃星辰推出全新基础大模型 Step 3，参数量高达 321B",
    "type": "topic",
    "up": false,
    "date": "2025-08-01 00:55:41",
    "uuid": "ab8ac5ce-abe9-4660-bc0d-302ef48659f4"
  },
  {
    "newsArray": [
      { "siteName": "财联社" },
      { "siteName": "格隆汇" },
      { "siteName": "第一财经" }
    ],
    "summary": "上海诺瓦聚变近日完成超过5亿元天使轮融资，由多家知名基金领投。公司专注于FRC-SMR技术研发，计划短期内实现1亿度离子聚变温度，中期达成聚变能量增益Q＞1，长期目标是在2035年实现模块化聚变电站商业化。",
    "id": "8lRrmTvofdF",
    "order": 1753979918290,
    "createdAt": "2025-07-31T16:38:47.000Z",
    "publishDate": "2025-07-31T16:38:38.290Z",
    "title": "上海诺瓦聚变已完成天使轮，金额超5亿元",
    "type": "topic",
    "up": false,
    "date": "2025-08-01 00:38:47",
    "uuid": "755617ce-51aa-4b0c-9de0-a148759a4c0d"
  },
  {
    "newsArray": [
      { "siteName": "格隆汇" },
      { "siteName": "IT 之家" },
      { "siteName": "第一财经" },
      { "siteName": "华尔街见闻" },
      { "siteName": "快科技" }
    ],
    "summary": "英伟达回应算力芯片存在安全问题，称其芯片无“后门”，不会允许远程访问或控制。为保障中国用户网络安全，国家互联网信息办公室约谈英伟达，要求其就对华销售的H20芯片的安全风险问题进行说明并提交证明材料。",
    "id": "8lRrQE6YzlK",
    "order": 1753979918502,
    "createdAt": "2025-07-31T16:35:43.000Z",
    "publishDate": "2025-07-31T16:38:38.502Z",
    "title": "英伟达深夜回应芯片“后门”问题：不会让任何人有远程访问或控制这些芯片的途径",
    "type": "topic",
    "up": false,
    "date": "2025-08-01 00:35:43",
    "uuid": "0422dfe6-60e1-4d00-a7c1-9d217e698740"
  },
  {
    "newsArray": [
      { "siteName": "中国科技网" },
      { "siteName": "IT 之家" },
      { "siteName": "格隆汇" }
    ],
    "summary": "2025年上半年，我国可再生能源新增装机2.68亿千瓦，同比增长99.3%，占新增装机的91.5% ...",
    "id": "8lQtsjYVMr1",
    "order": 1753977907664,
    "createdAt": "2025-07-31T16:08:10.000Z",
    "publishDate": "2025-07-31T16:05:07.664Z",
    "title": "国家能源局：可再生能源装机规模持续实现新突破",
    "type": "topic",
    "up": false,
    "date": "2025-08-01 00:08:10",
    "uuid": "3ded7133-fd65-4d7e-87fe-f133008b3ab7"
  }
]
