[
  {
    "newsArray": [
      { "siteName": "金融界" },
      { "siteName": "格隆汇" },
      { "siteName": "财联社" }
    ],
    "summary": "投行BAIRD将Meta Platforms目标价从820美元下调至815美元。",
    "id": "8pJoiMQmfOp",
    "order": 1766529713781,
    "createdAt": "2025-12-23T22:41:53.000Z",
    "publishDate": "2025-12-23T22:41:53.781Z",
    "title": "BAIRD：将Meta目标价下调至815美元",
    "type": "topic",
    "up": false,
    "date": "2025-12-24 06:41:53",
    "uuid": "95b69941-d2ca-4d75-8883-413d741376f4"
  },
  {
    "newsArray": [
      { "siteName": "华尔街见闻" },
      { "siteName": "财联社" },
      { "siteName": "界面" },
      { "siteName": "财联社" },
      { "siteName": "格隆汇" }
    ],
    "summary": "阳江海事局发布航行警告，12月24日8时至26日16时，南海部分海域进行火箭发射，禁止驶入。",
    "id": "8pKI6GzMVsi",
    "order": 1766528558868,
    "createdAt": "2025-12-23T22:22:39.000Z",
    "publishDate": "2025-12-23T22:22:38.868Z",
    "title": "航行警告：南海部分海域进行火箭发射，禁止驶入",
    "type": "topic",
    "up": false,
    "date": "2025-12-24 06:22:39",
    "uuid": "feb3094d-6dd8-4ad6-854e-71c1209ecff5"
  },
  {
    "newsArray": [
      { "siteName": "格隆汇" },
      { "siteName": "华尔街见闻" },
      { "siteName": "华尔街见闻" },
      { "siteName": "华尔街见闻" }
    ],
    "summary": "周二（12月23日）欧市尾盘，英国10年期国债收益率跌2.8个基点报4.508%，20:00刷新日低至4.491%后一度收窄跌幅 ...",
    "id": "8pKZFrNhCR5",
    "order": 1766528502798,
    "createdAt": "2025-12-23T20:42:49.000Z",
    "publishDate": "2025-12-23T22:21:42.798Z",
    "title": "中长期英债收益率跌约3个基点，美国GDP等数据发布后冲高回落",
    "type": "topic",
    "up": false,
    "date": "2025-12-24 04:42:49",
    "uuid": "fb5c37e4-9df7-4e36-b7fc-8f0498a02411"
  },
  {
    "newsArray": [
      { "siteName": "华尔街见闻" },
      { "siteName": "36Kr" },
      { "siteName": "格隆汇" }
    ],
    "summary": "英国政府将农民和企业的遗产税减免门槛提高至250万英镑，此举将大幅减少面临更高遗产税账单的农场和企业主数量。",
    "id": "8pKAr9UxSCy",
    "order": 1766516703158,
    "createdAt": "2025-12-23T19:05:04.000Z",
    "publishDate": "2025-12-23T19:05:03.158Z",
    "title": "英国政府：农民和企业的遗产税减免门槛将提高至250万英镑",
    "type": "topic",
    "up": false,
    "date": "2025-12-24 03:05:04",
    "uuid": "bdf949a7-4548-4fc0-8d7a-5d9209609fcf"
  },
  {
    "newsArray": [
      { "siteName": "华尔街见闻" },
      { "siteName": "财联社" },
      { "siteName": "格隆汇" }
    ],
    "summary": "当地时间12月23日，塞尔维亚总统武契奇称，塞尔维亚与俄罗斯就天然气供应达成一致，现有协议延长至2026年3月31日，确保冬季能源供应安全，保障居民生活和经济运行，民众无需担心短缺问题，当前能源保障形势总体稳定，国家已做好应对准备 ...",
    "id": "8pKes0BfmU1",
    "order": 1766516690444,
    "createdAt": "2025-12-23T19:04:50.000Z",
    "publishDate": "2025-12-23T19:04:50.444Z",
    "title": "武契奇：塞尔维亚与俄罗斯天然气供应协议延至明年3月底",
    "type": "topic",
    "up": false,
    "date": "2025-12-24 03:04:50",
    "uuid": "70945aab-1f4b-4f02-9166-eed8f3fdacca"
  },
  {
    "newsArray": [
      { "siteName": "华尔街见闻" },
      { "siteName": "财联社" },
      { "siteName": "界面" },
      { "siteName": "格隆汇" },
      { "siteName": "格隆汇" }
    ],
    "summary": "现货白银日内涨幅扩大至3%，报71.09美元/盎司，续创新高。现货黄金日内涨幅扩大至1%，报4488.02美元/盎司。",
    "id": "8pKKr9ANRCm",
    "order": 1766516588056,
    "createdAt": "2025-12-23T19:03:09.000Z",
    "publishDate": "2025-12-23T19:03:08.056Z",
    "title": "现货白银日内涨幅扩大至3% 续创新高",
    "type": "topic",
    "up": false,
    "date": "2025-12-24 03:03:09",
    "uuid": "f1e13b62-e88d-4a68-81ab-38b2ae938733"
  },
  {
    "newsArray": [
      { "siteName": "财联社" },
      { "siteName": "格隆汇" },
      { "siteName": "钛媒体" },
      { "siteName": "格隆汇" }
    ],
    "summary": "美国天然气期货日内涨幅达3%，现报4.084美元/百万英热。",
    "id": "8pKGZuosVTQ",
    "order": 1766514828117,
    "createdAt": "2025-12-23T18:33:48.000Z",
    "publishDate": "2025-12-23T18:33:48.117Z",
    "title": "美国天然气期货日内涨幅达3%，现报4.084美元/百万英热",
    "type": "topic",
    "up": false,
    "date": "2025-12-24 02:33:48",
    "uuid": "b45413b2-511e-4a4d-9995-ac4013e33605"
  },
  {
    "newsArray": [
      { "siteName": "华尔街见闻" },
      { "siteName": "华尔街见闻" },
      { "siteName": "华尔街见闻" },
      { "siteName": "格隆汇" }
    ],
    "summary": "美国财政部拍卖六周期国债，得标利率3.580%，投标倍数2.87。拍卖52周期国债，得标利率3.380%，投标倍数3.74。",
    "id": "8pKXiKZt5Az",
    "order": 1766513035310,
    "createdAt": "2025-12-23T18:03:55.000Z",
    "publishDate": "2025-12-23T18:03:55.310Z",
    "title": "美国财政部拍卖六周期国债",
    "type": "topic",
    "up": false,
    "date": "2025-12-24 02:03:55",
    "uuid": "ce44e4cb-5259-460a-b334-1115f2a0d331"
  },
  {
    "newsArray": [
      { "siteName": "格隆汇" },
      { "siteName": "财联社" },
      { "siteName": "华尔街见闻" }
    ],
    "summary": "欧洲STOXX 600指数初步收涨0.38%，报588.96点。欧元区STOXX 50指数初步收涨0.07%，报5747.59点 ...",
    "id": "8pKX5YPPkXi",
    "order": 1766508711367,
    "createdAt": "2025-12-23T16:51:51.000Z",
    "publishDate": "2025-12-23T16:51:51.367Z",
    "title": "欧洲股市收涨约0.4%",
    "type": "topic",
    "up": false,
    "date": "2025-12-24 00:51:51",
    "uuid": "68d5006f-720c-436c-b748-b070bea6727c"
  },
  {
    "newsArray": [
      { "siteName": "中国科技网" },
      { "siteName": "科学网" },
      { "siteName": "IT 之家" }
    ],
    "summary": "中国科学技术大学潘建伟、朱晓波等团队基于超导量子处理器“祖冲之3.2号”，在码距为7的表面码上实现低于纠错阈值的量子纠错，演示了逻辑错误率随码距增加显著下降，达到“低于阈值，越纠越对”的关键里程碑，开辟“全微波控制”新路径 ...",
    "id": "8pIoXA8R2BY",
    "order": 1766505812967,
    "createdAt": "2025-12-23T16:03:35.000Z",
    "publishDate": "2025-12-23T16:03:32.967Z",
    "title": "我国在量子纠错领域达到关键里程碑",
    "type": "topic",
    "up": false,
    "date": "2025-12-24 00:03:35",
    "uuid": "dcbb83d2-d48d-489a-a804-22895ed2ec37"
  }
]
